[
  {
    "time": "2025/07/18 00:32:22",
    "hots": [
      {
        "rank": 0,
        "topic": "走出一条中国特色城市现代化新路子",
        "score": 0,
        "tag": "top"
      },
      {
        "rank": 1,
        "topic": "肖战直播",
        "score": 850541,
        "tag": ""
      },
      {
        "rank": 2,
        "topic": "山姆背叛了山姆",
        "score": 315635,
        "tag": ""
      },
      {
        "rank": 3,
        "topic": "录取通知书是大学的第一堂课",
        "score": 294901,
        "tag": ""
      },
      {
        "rank": 4,
        "topic": "上海暴雨",
        "score": 285752,
        "tag": ""
      },
      {
        "rank": 5,
        "topic": "谢霆锋认为比赛用火锅底料是作弊",
        "score": 232533,
        "tag": ""
      },
      {
        "rank": 6,
        "topic": "余杭水务回应臭水事件赔偿问题",
        "score": 231057,
        "tag": ""
      },
      {
        "rank": 7,
        "topic": "被家暴16次女子前婆婆被判返还91万",
        "score": 228082,
        "tag": ""
      },
      {
        "rank": 8,
        "topic": "谢娜父母女儿爱人工作的排序",
        "score": 227128,
        "tag": "综艺"
      },
      {
        "rank": 9,
        "topic": "开网约车接到了歌手总导演",
        "score": 205939,
        "tag": "综艺"
      },
      {
        "rank": 10,
        "topic": "余杭居民称淋浴后全身都是臭的",
        "score": 204636,
        "tag": ""
      },
      {
        "rank": 11,
        "topic": "宝剑嫂雨哥分手",
        "score": 202043,
        "tag": ""
      },
      {
        "rank": 12,
        "topic": "网红阿家高考成绩462分",
        "score": 196905,
        "tag": ""
      },
      {
        "rank": 13,
        "topic": "网红老板西藏自驾途中去世",
        "score": 194328,
        "tag": ""
      },
      {
        "rank": 14,
        "topic": "马云骑车夜游西湖",
        "score": 193438,
        "tag": ""
      },
      {
        "rank": 15,
        "topic": "BLG对战G2",
        "score": 174595,
        "tag": ""
      },
      {
        "rank": 16,
        "topic": "邓为戏服",
        "score": 167104,
        "tag": "剧集"
      },
      {
        "rank": 17,
        "topic": "AG对战TTG",
        "score": 166357,
        "tag": ""
      },
      {
        "rank": 18,
        "topic": "21岁女孩患癌后的第一次短暂自由",
        "score": 157798,
        "tag": ""
      },
      {
        "rank": 19,
        "topic": "蔡徐坤新发色",
        "score": 148207,
        "tag": ""
      },
      {
        "rank": 20,
        "topic": "AG战胜HLE",
        "score": 142342,
        "tag": ""
      },
      {
        "rank": 21,
        "topic": "殡仪馆3500招太平间门卫要全天在岗",
        "score": 139737,
        "tag": ""
      },
      {
        "rank": 22,
        "topic": "朝雪录",
        "score": 136046,
        "tag": "剧集"
      },
      {
        "rank": 23,
        "topic": "600分扎堆本升专",
        "score": 135187,
        "tag": ""
      },
      {
        "rank": 24,
        "topic": "爱奇艺717",
        "score": 126587,
        "tag": ""
      },
      {
        "rank": 25,
        "topic": "游客为拍照不慎将孩子撞落水",
        "score": 126559,
        "tag": ""
      },
      {
        "rank": 26,
        "topic": "祝绪丹回应被说装可爱",
        "score": 126166,
        "tag": ""
      },
      {
        "rank": 27,
        "topic": "中美两国人民完全可以成为好朋友",
        "score": 122801,
        "tag": ""
      },
      {
        "rank": 28,
        "topic": "樱桃琥珀原著 避孕药",
        "score": 120750,
        "tag": "剧集"
      },
      {
        "rank": 29,
        "topic": "肖战强迫症好夸张",
        "score": 114830,
        "tag": ""
      },
      {
        "rank": 30,
        "topic": "香港禁烟设施也太超前了",
        "score": 113163,
        "tag": ""
      },
      {
        "rank": 31,
        "topic": "多地明确婚假延长引发热议",
        "score": 112073,
        "tag": ""
      },
      {
        "rank": 32,
        "topic": "河南蚊子被热死",
        "score": 97881,
        "tag": ""
      },
      {
        "rank": 33,
        "topic": "李昀锐秀肌肉",
        "score": 96521,
        "tag": ""
      },
      {
        "rank": 34,
        "topic": "官方回应进丽江古城要交50元",
        "score": 94109,
        "tag": ""
      },
      {
        "rank": 35,
        "topic": "白鹿对接回应叶璃妆造争议",
        "score": 93285,
        "tag": "剧集"
      },
      {
        "rank": 36,
        "topic": "密室大逃脱大神版",
        "score": 92098,
        "tag": "综艺"
      },
      {
        "rank": 37,
        "topic": "乐山大佛热到休假了",
        "score": 88697,
        "tag": ""
      },
      {
        "rank": 38,
        "topic": "张艺凡的腿",
        "score": 73444,
        "tag": ""
      },
      {
        "rank": 39,
        "topic": "高温补贴",
        "score": 69557,
        "tag": ""
      },
      {
        "rank": 40,
        "topic": "山姆选品降级到底藏着多少猫腻",
        "score": 68552,
        "tag": ""
      },
      {
        "rank": 41,
        "topic": "武侠剧要回来了",
        "score": 68460,
        "tag": ""
      },
      {
        "rank": 42,
        "topic": "成都AG沙漠图吃鸡",
        "score": 64661,
        "tag": ""
      },
      {
        "rank": 43,
        "topic": "打歌2025",
        "score": 64028,
        "tag": ""
      },
      {
        "rank": 44,
        "topic": "被家暴16次女子最新发声",
        "score": 63224,
        "tag": ""
      },
      {
        "rank": 45,
        "topic": "小猫要一辈子崇拜你了",
        "score": 61922,
        "tag": ""
      },
      {
        "rank": 46,
        "topic": "一国企登报喊61名职工回来上班",
        "score": 61642,
        "tag": ""
      },
      {
        "rank": 47,
        "topic": "奥巴马夫妇回应离婚传闻",
        "score": 59325,
        "tag": ""
      },
      {
        "rank": 48,
        "topic": "王楚钦秀胯下击球",
        "score": 57829,
        "tag": ""
      },
      {
        "rank": 49,
        "topic": "孙颖莎要以身作则激励年轻一代",
        "score": 57331,
        "tag": ""
      },
      {
        "rank": 50,
        "topic": "AG碾碎HLE钥匙",
        "score": 57300,
        "tag": ""
      }
    ]
  }
]