[
  {
    "time": "2025/08/11 00:29:25",
    "hots": [
      {
        "rank": 0,
        "topic": "积极促进产业高端化智能化绿色化",
        "score": 0,
        "tag": "top"
      },
      {
        "rank": 1,
        "topic": "全球首个孕育机器人预计一年内面世",
        "score": 935715,
        "tag": ""
      },
      {
        "rank": 2,
        "topic": "展轩空降",
        "score": 834737,
        "tag": ""
      },
      {
        "rank": 3,
        "topic": "相约成都遇见万千精彩",
        "score": 585854,
        "tag": ""
      },
      {
        "rank": 4,
        "topic": "婚内强奸案男方姐姐发声",
        "score": 403352,
        "tag": ""
      },
      {
        "rank": 5,
        "topic": "蔡徐坤 Jasmine",
        "score": 373057,
        "tag": "音乐"
      },
      {
        "rank": 6,
        "topic": "张本智和回应告状",
        "score": 335371,
        "tag": ""
      },
      {
        "rank": 7,
        "topic": "拉宏桑妈妈怀孕后还吃了打虫药",
        "score": 335234,
        "tag": "综艺"
      },
      {
        "rank": 8,
        "topic": "利剑玫瑰第二季",
        "score": 332413,
        "tag": ""
      },
      {
        "rank": 9,
        "topic": "社保新规对打工人有何影响",
        "score": 294846,
        "tag": ""
      },
      {
        "rank": 10,
        "topic": "这不是复制粘贴这是中国军人",
        "score": 204101,
        "tag": ""
      },
      {
        "rank": 11,
        "topic": "曝孙亦航恋情",
        "score": 202749,
        "tag": ""
      },
      {
        "rank": 12,
        "topic": "张本智和不满王皓握手敷衍",
        "score": 201886,
        "tag": ""
      },
      {
        "rank": 13,
        "topic": "向往的生活8",
        "score": 199639,
        "tag": "综艺"
      },
      {
        "rank": 14,
        "topic": "女子试穿4条裤子留下血渍赔50元",
        "score": 195571,
        "tag": ""
      },
      {
        "rank": 15,
        "topic": "白桃星座一周运势",
        "score": 195377,
        "tag": ""
      },
      {
        "rank": 16,
        "topic": "浪浪山小妖怪",
        "score": 195204,
        "tag": "电影"
      },
      {
        "rank": 17,
        "topic": "虞书欣机场私服好健康的美",
        "score": 169531,
        "tag": ""
      },
      {
        "rank": 18,
        "topic": "抗战胜利80周年天安门演练现场",
        "score": 165146,
        "tag": ""
      },
      {
        "rank": 19,
        "topic": "锦月如歌热度",
        "score": 161514,
        "tag": "剧集"
      },
      {
        "rank": 20,
        "topic": "女子看演出时遭猥亵嫌疑人被刑拘",
        "score": 159757,
        "tag": ""
      },
      {
        "rank": 21,
        "topic": "张晋和蔡少芬国外旅行突发心脏病",
        "score": 159158,
        "tag": "综艺"
      },
      {
        "rank": 22,
        "topic": "关晓彤瘦了十几斤",
        "score": 157135,
        "tag": ""
      },
      {
        "rank": 23,
        "topic": "小蝴蝶Cody领证",
        "score": 118072,
        "tag": ""
      },
      {
        "rank": 24,
        "topic": "贺峻霖甜椒撕拉片",
        "score": 115580,
        "tag": ""
      },
      {
        "rank": 25,
        "topic": "社区盾杯",
        "score": 115267,
        "tag": ""
      },
      {
        "rank": 26,
        "topic": "妻子嫂子景德镇批发式购物狂买2000元",
        "score": 114875,
        "tag": ""
      },
      {
        "rank": 27,
        "topic": "男子疑将660万彩票丢进洗衣机",
        "score": 113816,
        "tag": ""
      },
      {
        "rank": 28,
        "topic": "于正说赵露思很好",
        "score": 110691,
        "tag": ""
      },
      {
        "rank": 29,
        "topic": "建议多囊还是不要参与外卖大战了",
        "score": 105836,
        "tag": ""
      },
      {
        "rank": 30,
        "topic": "杭州警方通报某演出场所发生猥亵事件",
        "score": 101140,
        "tag": ""
      },
      {
        "rank": 31,
        "topic": "CORTIS出道曲MV",
        "score": 101049,
        "tag": "音乐"
      },
      {
        "rank": 32,
        "topic": "汪苏泷这段完全是婚礼VCR",
        "score": 98782,
        "tag": "演出"
      },
      {
        "rank": 33,
        "topic": "李河民大屏生图",
        "score": 98259,
        "tag": "演出"
      },
      {
        "rank": 34,
        "topic": "网友票选可以出道的星二代",
        "score": 87810,
        "tag": ""
      },
      {
        "rank": 35,
        "topic": "向往的生活8 丁程鑫",
        "score": 87223,
        "tag": "综艺"
      },
      {
        "rank": 36,
        "topic": "抠抠搜搜8年抠了49万",
        "score": 84270,
        "tag": ""
      },
      {
        "rank": 37,
        "topic": "周深唱了两首贾玲电影的代表曲",
        "score": 83883,
        "tag": "演出"
      },
      {
        "rank": 38,
        "topic": "2岁男童把疏通剂当玩具双手差点不保",
        "score": 81750,
        "tag": ""
      },
      {
        "rank": 39,
        "topic": "26岁男子勒死73岁情人水泥埋尸",
        "score": 80531,
        "tag": ""
      },
      {
        "rank": 40,
        "topic": "社区盾杯决赛",
        "score": 78232,
        "tag": ""
      },
      {
        "rank": 41,
        "topic": "溺亡女童左腿被回水管吸住",
        "score": 75966,
        "tag": ""
      },
      {
        "rank": 42,
        "topic": "百果园 钟薛高",
        "score": 73842,
        "tag": ""
      },
      {
        "rank": 43,
        "topic": "为什么叫我法拉利",
        "score": 73282,
        "tag": ""
      },
      {
        "rank": 44,
        "topic": "水晶宫vs利物浦",
        "score": 72177,
        "tag": ""
      },
      {
        "rank": 45,
        "topic": "早春晴朗男主85生",
        "score": 72019,
        "tag": ""
      },
      {
        "rank": 46,
        "topic": "陈哲远这次是真老公",
        "score": 71780,
        "tag": ""
      },
      {
        "rank": 47,
        "topic": "那英去花少带了更年期的药",
        "score": 71382,
        "tag": "综艺"
      },
      {
        "rank": 48,
        "topic": "CORTIS BIGHIT",
        "score": 67671,
        "tag": ""
      },
      {
        "rank": 49,
        "topic": "王烁然 四代",
        "score": 65836,
        "tag": ""
      },
      {
        "rank": 50,
        "topic": "孙颖莎厉害是藏不住",
        "score": 64459,
        "tag": ""
      }
    ]
  },
  {
    "time": "2025/08/11 01:20:14",
    "hots": [
      {
        "rank": 0,
        "topic": "积极促进产业高端化智能化绿色化",
        "score": 0,
        "tag": "top"
      },
      {
        "rank": 1,
        "topic": "全球首个孕育机器人预计一年内面世",
        "score": 517657,
        "tag": ""
      },
      {
        "rank": 2,
        "topic": "展轩空降",
        "score": 310397,
        "tag": ""
      },
      {
        "rank": 3,
        "topic": "来天津感受河海津韵",
        "score": 302768,
        "tag": ""
      },
      {
        "rank": 4,
        "topic": "店员回应男子误将660万彩票洗成渣",
        "score": 296177,
        "tag": ""
      },
      {
        "rank": 5,
        "topic": "拉宏桑妈妈怀孕后还吃了打虫药",
        "score": 206368,
        "tag": "综艺"
      },
      {
        "rank": 6,
        "topic": "张本智和回应告状",
        "score": 153776,
        "tag": ""
      },
      {
        "rank": 7,
        "topic": "锦月如歌热度",
        "score": 152152,
        "tag": "剧集"
      },
      {
        "rank": 8,
        "topic": "蔡徐坤 Jasmine",
        "score": 151003,
        "tag": "音乐"
      },
      {
        "rank": 9,
        "topic": "婚内强奸案男方姐姐发声",
        "score": 146838,
        "tag": ""
      },
      {
        "rank": 10,
        "topic": "社保新规对打工人有何影响",
        "score": 105523,
        "tag": ""
      },
      {
        "rank": 11,
        "topic": "曝孙亦航恋情",
        "score": 105496,
        "tag": ""
      },
      {
        "rank": 12,
        "topic": "张本智和不满王皓握手敷衍",
        "score": 105443,
        "tag": ""
      },
      {
        "rank": 13,
        "topic": "利剑玫瑰第二季",
        "score": 105368,
        "tag": ""
      },
      {
        "rank": 14,
        "topic": "向往的生活8",
        "score": 105326,
        "tag": "综艺"
      },
      {
        "rank": 15,
        "topic": "女子试穿4条裤子留下血渍赔50元",
        "score": 105226,
        "tag": ""
      },
      {
        "rank": 16,
        "topic": "浪浪山小妖怪",
        "score": 105189,
        "tag": "电影"
      },
      {
        "rank": 17,
        "topic": "这不是复制粘贴这是中国军人",
        "score": 105156,
        "tag": ""
      },
      {
        "rank": 18,
        "topic": "白桃星座一周运势",
        "score": 86862,
        "tag": ""
      },
      {
        "rank": 19,
        "topic": "抗战胜利80周年天安门演练现场",
        "score": 85234,
        "tag": ""
      },
      {
        "rank": 20,
        "topic": "虞书欣机场私服好健康的美",
        "score": 83317,
        "tag": ""
      },
      {
        "rank": 21,
        "topic": "建议多囊还是不要参与外卖大战了",
        "score": 79032,
        "tag": ""
      },
      {
        "rank": 22,
        "topic": "张晋和蔡少芬国外旅行突发心脏病",
        "score": 71962,
        "tag": "综艺"
      },
      {
        "rank": 23,
        "topic": "幼童爬到13层阳台外悬空玩引体向上",
        "score": 71959,
        "tag": ""
      },
      {
        "rank": 24,
        "topic": "贺峻霖甜椒撕拉片",
        "score": 71955,
        "tag": ""
      },
      {
        "rank": 25,
        "topic": "关晓彤瘦了十几斤",
        "score": 71952,
        "tag": ""
      },
      {
        "rank": 26,
        "topic": "于正说赵露思很好",
        "score": 71948,
        "tag": ""
      },
      {
        "rank": 27,
        "topic": "杭州警方通报某演出场所发生猥亵事件",
        "score": 71943,
        "tag": ""
      },
      {
        "rank": 28,
        "topic": "女子看演出时遭猥亵嫌疑人被刑拘",
        "score": 71936,
        "tag": ""
      },
      {
        "rank": 29,
        "topic": "你的提神饮料正悄悄让你变胖",
        "score": 71930,
        "tag": ""
      },
      {
        "rank": 30,
        "topic": "巴黎合伙人",
        "score": 71928,
        "tag": "综艺"
      },
      {
        "rank": 31,
        "topic": "网友票选可以出道的星二代",
        "score": 71923,
        "tag": ""
      },
      {
        "rank": 32,
        "topic": "妻子嫂子景德镇批发式购物狂买2000元",
        "score": 71919,
        "tag": ""
      },
      {
        "rank": 33,
        "topic": "百果园 钟薛高",
        "score": 71913,
        "tag": ""
      },
      {
        "rank": 34,
        "topic": "向往的生活8 丁程鑫",
        "score": 71908,
        "tag": "综艺"
      },
      {
        "rank": 35,
        "topic": "CORTIS出道曲MV",
        "score": 71902,
        "tag": "音乐"
      },
      {
        "rank": 36,
        "topic": "26岁男子勒死73岁情人水泥埋尸",
        "score": 71899,
        "tag": ""
      },
      {
        "rank": 37,
        "topic": "汪苏泷说西安也有罗曼城定位了",
        "score": 71893,
        "tag": "演出"
      },
      {
        "rank": 38,
        "topic": "小蝴蝶Cody领证",
        "score": 71889,
        "tag": ""
      },
      {
        "rank": 39,
        "topic": "谢霆锋杭州演唱会",
        "score": 71884,
        "tag": "演出"
      },
      {
        "rank": 40,
        "topic": "汪苏泷这段完全是婚礼VCR",
        "score": 71880,
        "tag": "演出"
      },
      {
        "rank": 41,
        "topic": "秦海璐嫂子爆改犁地小生",
        "score": 71876,
        "tag": ""
      },
      {
        "rank": 42,
        "topic": "2岁男童把疏通剂当玩具双手差点不保",
        "score": 71871,
        "tag": ""
      },
      {
        "rank": 43,
        "topic": "为什么叫我法拉利",
        "score": 71865,
        "tag": ""
      },
      {
        "rank": 44,
        "topic": "周深唱了两首贾玲电影的代表曲",
        "score": 71862,
        "tag": "演出"
      },
      {
        "rank": 45,
        "topic": "男子疑将660万彩票丢进洗衣机",
        "score": 71857,
        "tag": ""
      },
      {
        "rank": 46,
        "topic": "早春晴朗男主85生",
        "score": 71853,
        "tag": ""
      },
      {
        "rank": 47,
        "topic": "抠抠搜搜8年抠了49万",
        "score": 71850,
        "tag": ""
      },
      {
        "rank": 48,
        "topic": "逆水寒",
        "score": 71844,
        "tag": ""
      },
      {
        "rank": 49,
        "topic": "AG战胜狼队",
        "score": 71839,
        "tag": ""
      },
      {
        "rank": 50,
        "topic": "吃到腾讯芒果商战红利了",
        "score": 71837,
        "tag": "剧集"
      }
    ]
  },
  {
    "time": "2025/08/11 02:32:52",
    "hots": [
      {
        "rank": 0,
        "topic": "积极促进产业高端化智能化绿色化",
        "score": 0,
        "tag": "top"
      },
      {
        "rank": 1,
        "topic": "全球首个孕育机器人预计一年内面世",
        "score": 182918,
        "tag": ""
      },
      {
        "rank": 2,
        "topic": "店员回应男子误将660万彩票洗成渣",
        "score": 144103,
        "tag": ""
      },
      {
        "rank": 3,
        "topic": "来天津感受河海津韵",
        "score": 126052,
        "tag": ""
      },
      {
        "rank": 4,
        "topic": "拉宏桑妈妈怀孕后还吃了打虫药",
        "score": 118146,
        "tag": "综艺"
      },
      {
        "rank": 5,
        "topic": "男子偷580斤西瓜都吃光",
        "score": 103072,
        "tag": ""
      },
      {
        "rank": 6,
        "topic": "幼童爬到13层阳台外悬空玩引体向上",
        "score": 80307,
        "tag": ""
      },
      {
        "rank": 7,
        "topic": "展轩空降",
        "score": 78658,
        "tag": ""
      },
      {
        "rank": 8,
        "topic": "张本智和回应告状",
        "score": 72168,
        "tag": ""
      },
      {
        "rank": 9,
        "topic": "锦月如歌热度",
        "score": 66613,
        "tag": "剧集"
      },
      {
        "rank": 10,
        "topic": "土耳其6.3级地震",
        "score": 63243,
        "tag": ""
      },
      {
        "rank": 11,
        "topic": "陶白白前妻称如果为了钱就不会离婚",
        "score": 60393,
        "tag": ""
      },
      {
        "rank": 12,
        "topic": "曝孙亦航恋情",
        "score": 58910,
        "tag": ""
      },
      {
        "rank": 13,
        "topic": "张本智和不满王皓握手敷衍",
        "score": 54739,
        "tag": ""
      },
      {
        "rank": 14,
        "topic": "浪浪山小妖怪",
        "score": 52289,
        "tag": "电影"
      },
      {
        "rank": 15,
        "topic": "向往的生活8",
        "score": 51178,
        "tag": "综艺"
      },
      {
        "rank": 16,
        "topic": "社保新规对打工人有何影响",
        "score": 49278,
        "tag": ""
      },
      {
        "rank": 17,
        "topic": "女子试穿4条裤子留下血渍赔50元",
        "score": 48227,
        "tag": ""
      },
      {
        "rank": 18,
        "topic": "利剑玫瑰第二季",
        "score": 48186,
        "tag": ""
      },
      {
        "rank": 19,
        "topic": "婚内强奸案男方姐姐发声",
        "score": 47232,
        "tag": ""
      },
      {
        "rank": 20,
        "topic": "虞书欣机场私服好健康的美",
        "score": 45837,
        "tag": ""
      },
      {
        "rank": 21,
        "topic": "蔡徐坤 Jasmine",
        "score": 43985,
        "tag": "音乐"
      },
      {
        "rank": 22,
        "topic": "张晋和蔡少芬国外旅行突发心脏病",
        "score": 37862,
        "tag": "综艺"
      },
      {
        "rank": 23,
        "topic": "于正说赵露思很好",
        "score": 37856,
        "tag": ""
      },
      {
        "rank": 24,
        "topic": "杭州警方通报某演出场所发生猥亵事件",
        "score": 37810,
        "tag": ""
      },
      {
        "rank": 25,
        "topic": "建议多囊还是不要参与外卖大战了",
        "score": 36126,
        "tag": ""
      },
      {
        "rank": 26,
        "topic": "网友票选可以出道的星二代",
        "score": 36124,
        "tag": ""
      },
      {
        "rank": 27,
        "topic": "贺峻霖甜椒撕拉片",
        "score": 36123,
        "tag": ""
      },
      {
        "rank": 28,
        "topic": "白桃星座一周运势",
        "score": 36123,
        "tag": ""
      },
      {
        "rank": 29,
        "topic": "女子看演出时遭猥亵嫌疑人被刑拘",
        "score": 36121,
        "tag": ""
      },
      {
        "rank": 30,
        "topic": "这不是复制粘贴这是中国军人",
        "score": 36119,
        "tag": ""
      },
      {
        "rank": 31,
        "topic": "百果园 钟薛高",
        "score": 36116,
        "tag": ""
      },
      {
        "rank": 32,
        "topic": "逆水寒",
        "score": 36115,
        "tag": ""
      },
      {
        "rank": 33,
        "topic": "向往的生活8 丁程鑫",
        "score": 36114,
        "tag": "综艺"
      },
      {
        "rank": 34,
        "topic": "吃到腾讯芒果商战红利了",
        "score": 36113,
        "tag": "剧集"
      },
      {
        "rank": 35,
        "topic": "关晓彤瘦了十几斤",
        "score": 36111,
        "tag": ""
      },
      {
        "rank": 36,
        "topic": "妻子嫂子景德镇批发式购物狂买2000元",
        "score": 36110,
        "tag": ""
      },
      {
        "rank": 37,
        "topic": "汪苏泷唱了你最近好吗",
        "score": 36107,
        "tag": "演出"
      },
      {
        "rank": 38,
        "topic": "巴黎合伙人",
        "score": 36105,
        "tag": "综艺"
      },
      {
        "rank": 39,
        "topic": "溺亡女童左腿被回水管吸住",
        "score": 36105,
        "tag": ""
      },
      {
        "rank": 40,
        "topic": "AG战胜狼队",
        "score": 36102,
        "tag": ""
      },
      {
        "rank": 41,
        "topic": "你的提神饮料正悄悄让你变胖",
        "score": 36101,
        "tag": ""
      },
      {
        "rank": 42,
        "topic": "CORTIS出道曲MV",
        "score": 36100,
        "tag": "音乐"
      },
      {
        "rank": 43,
        "topic": "早春晴朗男主85生",
        "score": 36099,
        "tag": ""
      },
      {
        "rank": 44,
        "topic": "汪苏泷说西安也有罗曼城定位了",
        "score": 36096,
        "tag": "演出"
      },
      {
        "rank": 45,
        "topic": "抠抠搜搜8年抠了49万",
        "score": 36096,
        "tag": ""
      },
      {
        "rank": 46,
        "topic": "抗战胜利80周年天安门演练现场",
        "score": 36093,
        "tag": ""
      },
      {
        "rank": 47,
        "topic": "26岁男子勒死73岁情人水泥埋尸",
        "score": 36093,
        "tag": ""
      },
      {
        "rank": 48,
        "topic": "为什么叫我法拉利",
        "score": 36091,
        "tag": ""
      },
      {
        "rank": 49,
        "topic": "CORTIS BIGHIT",
        "score": 36089,
        "tag": ""
      },
      {
        "rank": 50,
        "topic": "周深唱了两首贾玲电影的代表曲",
        "score": 36088,
        "tag": "演出"
      }
    ]
  },
  {
    "time": "2025/08/11 03:18:59",
    "hots": [
      {
        "rank": 0,
        "topic": "积极促进产业高端化智能化绿色化",
        "score": 0,
        "tag": "top"
      },
      {
        "rank": 1,
        "topic": "男子偷580斤西瓜都吃光",
        "score": 160192,
        "tag": ""
      },
      {
        "rank": 2,
        "topic": "男子嫌太吵向楼下烧烤店泼不明液体",
        "score": 106627,
        "tag": ""
      },
      {
        "rank": 3,
        "topic": "来天津感受河海津韵",
        "score": 106131,
        "tag": ""
      },
      {
        "rank": 4,
        "topic": "陶白白前妻称如果为了钱就不会离婚",
        "score": 105689,
        "tag": ""
      },
      {
        "rank": 5,
        "topic": "全球首个孕育机器人预计一年内面世",
        "score": 97596,
        "tag": ""
      },
      {
        "rank": 6,
        "topic": "店员回应男子误将660万彩票洗成渣",
        "score": 72163,
        "tag": ""
      },
      {
        "rank": 7,
        "topic": "展轩空降",
        "score": 49639,
        "tag": ""
      },
      {
        "rank": 8,
        "topic": "幼童爬到13层阳台外悬空玩引体向上",
        "score": 45448,
        "tag": ""
      },
      {
        "rank": 9,
        "topic": "拉宏桑妈妈怀孕后还吃了打虫药",
        "score": 45162,
        "tag": "综艺"
      },
      {
        "rank": 10,
        "topic": "张本智和回应告状",
        "score": 36293,
        "tag": ""
      },
      {
        "rank": 11,
        "topic": "张本智和不满王皓握手敷衍",
        "score": 35792,
        "tag": ""
      },
      {
        "rank": 12,
        "topic": "曝孙亦航恋情",
        "score": 35406,
        "tag": ""
      },
      {
        "rank": 13,
        "topic": "土耳其6.3级地震",
        "score": 35337,
        "tag": ""
      },
      {
        "rank": 14,
        "topic": "向往的生活8",
        "score": 34565,
        "tag": "综艺"
      },
      {
        "rank": 15,
        "topic": "锦月如歌热度",
        "score": 34557,
        "tag": "剧集"
      },
      {
        "rank": 16,
        "topic": "社保新规对打工人有何影响",
        "score": 32876,
        "tag": ""
      },
      {
        "rank": 17,
        "topic": "虞书欣机场私服好健康的美",
        "score": 32037,
        "tag": ""
      },
      {
        "rank": 18,
        "topic": "女子试穿4条裤子留下血渍赔50元",
        "score": 31291,
        "tag": ""
      },
      {
        "rank": 19,
        "topic": "婚内强奸案男方姐姐发声",
        "score": 30894,
        "tag": ""
      },
      {
        "rank": 20,
        "topic": "浪浪山小妖怪",
        "score": 30892,
        "tag": "电影"
      },
      {
        "rank": 21,
        "topic": "蔡徐坤 Jasmine",
        "score": 30889,
        "tag": "音乐"
      },
      {
        "rank": 22,
        "topic": "于正说赵露思很好",
        "score": 30889,
        "tag": ""
      },
      {
        "rank": 23,
        "topic": "利剑玫瑰第二季",
        "score": 30887,
        "tag": ""
      },
      {
        "rank": 24,
        "topic": "张晋和蔡少芬国外旅行突发心脏病",
        "score": 30883,
        "tag": "综艺"
      },
      {
        "rank": 25,
        "topic": "贺峻霖甜椒撕拉片",
        "score": 30881,
        "tag": ""
      },
      {
        "rank": 26,
        "topic": "逆水寒",
        "score": 30879,
        "tag": ""
      },
      {
        "rank": 27,
        "topic": "女子看演出时遭猥亵嫌疑人被刑拘",
        "score": 30877,
        "tag": ""
      },
      {
        "rank": 28,
        "topic": "建议多囊还是不要参与外卖大战了",
        "score": 30875,
        "tag": ""
      },
      {
        "rank": 29,
        "topic": "杭州警方通报某演出场所发生猥亵事件",
        "score": 30874,
        "tag": ""
      },
      {
        "rank": 30,
        "topic": "这不是复制粘贴这是中国军人",
        "score": 30873,
        "tag": ""
      },
      {
        "rank": 31,
        "topic": "网友票选可以出道的星二代",
        "score": 30871,
        "tag": ""
      },
      {
        "rank": 32,
        "topic": "地球超新鲜",
        "score": 30866,
        "tag": "综艺"
      },
      {
        "rank": 33,
        "topic": "百果园 钟薛高",
        "score": 30866,
        "tag": ""
      },
      {
        "rank": 34,
        "topic": "AG战胜狼队",
        "score": 30864,
        "tag": ""
      },
      {
        "rank": 35,
        "topic": "妻子嫂子景德镇批发式购物狂买2000元",
        "score": 30862,
        "tag": ""
      },
      {
        "rank": 36,
        "topic": "白桃星座一周运势",
        "score": 30858,
        "tag": ""
      },
      {
        "rank": 37,
        "topic": "汪苏泷唱了你最近好吗",
        "score": 30856,
        "tag": "演出"
      },
      {
        "rank": 38,
        "topic": "吃到腾讯芒果商战红利了",
        "score": 30855,
        "tag": "剧集"
      },
      {
        "rank": 39,
        "topic": "百果园回应加盟店数量锐减",
        "score": 30853,
        "tag": ""
      },
      {
        "rank": 40,
        "topic": "你的提神饮料正悄悄让你变胖",
        "score": 30850,
        "tag": ""
      },
      {
        "rank": 41,
        "topic": "韩泰山自拍",
        "score": 30849,
        "tag": ""
      },
      {
        "rank": 42,
        "topic": "孙颖莎说今天回去要多吃一点",
        "score": 30847,
        "tag": ""
      },
      {
        "rank": 43,
        "topic": "办252桌婚宴后拒付52万当事方发声",
        "score": 30845,
        "tag": ""
      },
      {
        "rank": 44,
        "topic": "向往的生活8 丁程鑫",
        "score": 30841,
        "tag": "综艺"
      },
      {
        "rank": 45,
        "topic": "关晓彤瘦了十几斤",
        "score": 30839,
        "tag": ""
      },
      {
        "rank": 46,
        "topic": "汪苏泷唱了分手季节",
        "score": 30837,
        "tag": "演出"
      },
      {
        "rank": 47,
        "topic": "CORTIS出道曲MV",
        "score": 30835,
        "tag": "音乐"
      },
      {
        "rank": 48,
        "topic": "2岁男童把疏通剂当玩具双手差点不保",
        "score": 30834,
        "tag": ""
      },
      {
        "rank": 49,
        "topic": "为什么叫我法拉利",
        "score": 30831,
        "tag": ""
      },
      {
        "rank": 50,
        "topic": "抗战胜利80周年天安门演练现场",
        "score": 30831,
        "tag": ""
      }
    ]
  },
  {
    "time": "2025/08/11 04:26:11",
    "hots": [
      {
        "rank": 0,
        "topic": "积极促进产业高端化智能化绿色化",
        "score": 0,
        "tag": "top"
      },
      {
        "rank": 1,
        "topic": "男子嫌太吵向楼下烧烤店泼不明液体",
        "score": 106742,
        "tag": ""
      },
      {
        "rank": 2,
        "topic": "男子偷580斤西瓜都吃光",
        "score": 86926,
        "tag": ""
      },
      {
        "rank": 3,
        "topic": "来天津感受河海津韵",
        "score": 62263,
        "tag": ""
      },
      {
        "rank": 4,
        "topic": "陶白白前妻称如果为了钱就不会离婚",
        "score": 56252,
        "tag": ""
      },
      {
        "rank": 5,
        "topic": "全球首个孕育机器人预计一年内面世",
        "score": 54514,
        "tag": ""
      },
      {
        "rank": 6,
        "topic": "店员回应男子误将660万彩票洗成渣",
        "score": 45939,
        "tag": ""
      },
      {
        "rank": 7,
        "topic": "社保新规对打工人有何影响",
        "score": 35227,
        "tag": ""
      },
      {
        "rank": 8,
        "topic": "展轩空降",
        "score": 33585,
        "tag": ""
      },
      {
        "rank": 9,
        "topic": "蔡徐坤 Jasmine",
        "score": 30214,
        "tag": "音乐"
      },
      {
        "rank": 10,
        "topic": "婚内强奸案男方姐姐发声",
        "score": 29766,
        "tag": ""
      },
      {
        "rank": 11,
        "topic": "张本智和不满王皓握手敷衍",
        "score": 29755,
        "tag": ""
      },
      {
        "rank": 12,
        "topic": "曝孙亦航恋情",
        "score": 29744,
        "tag": ""
      },
      {
        "rank": 13,
        "topic": "拉宏桑妈妈怀孕后还吃了打虫药",
        "score": 29679,
        "tag": "综艺"
      },
      {
        "rank": 14,
        "topic": "幼童爬到13层阳台外悬空玩引体向上",
        "score": 27452,
        "tag": ""
      },
      {
        "rank": 15,
        "topic": "女子看演出时遭猥亵嫌疑人被刑拘",
        "score": 27135,
        "tag": ""
      },
      {
        "rank": 16,
        "topic": "土耳其6.3级地震",
        "score": 25741,
        "tag": ""
      },
      {
        "rank": 17,
        "topic": "向往的生活8",
        "score": 24931,
        "tag": "综艺"
      },
      {
        "rank": 18,
        "topic": "张本智和回应告状",
        "score": 23913,
        "tag": ""
      },
      {
        "rank": 19,
        "topic": "逆水寒",
        "score": 23401,
        "tag": ""
      },
      {
        "rank": 20,
        "topic": "虞书欣机场私服好健康的美",
        "score": 22227,
        "tag": ""
      },
      {
        "rank": 21,
        "topic": "张晋和蔡少芬国外旅行突发心脏病",
        "score": 20060,
        "tag": "综艺"
      },
      {
        "rank": 22,
        "topic": "杭州警方通报某演出场所发生猥亵事件",
        "score": 19929,
        "tag": ""
      },
      {
        "rank": 23,
        "topic": "浪浪山小妖怪",
        "score": 19678,
        "tag": "电影"
      },
      {
        "rank": 24,
        "topic": "孙颖莎说今天回去要多吃一点",
        "score": 19654,
        "tag": ""
      },
      {
        "rank": 25,
        "topic": "建议多囊还是不要参与外卖大战了",
        "score": 18837,
        "tag": ""
      },
      {
        "rank": 26,
        "topic": "网友票选可以出道的星二代",
        "score": 18624,
        "tag": ""
      },
      {
        "rank": 27,
        "topic": "地球超新鲜",
        "score": 18495,
        "tag": "综艺"
      },
      {
        "rank": 28,
        "topic": "贺峻霖甜椒撕拉片",
        "score": 18042,
        "tag": ""
      },
      {
        "rank": 29,
        "topic": "这不是复制粘贴这是中国军人",
        "score": 17993,
        "tag": ""
      },
      {
        "rank": 30,
        "topic": "办252桌婚宴后拒付52万当事方发声",
        "score": 17701,
        "tag": ""
      },
      {
        "rank": 31,
        "topic": "女子试穿4条裤子留下血渍赔50元",
        "score": 17267,
        "tag": ""
      },
      {
        "rank": 32,
        "topic": "于正说赵露思很好",
        "score": 17060,
        "tag": ""
      },
      {
        "rank": 33,
        "topic": "你的提神饮料正悄悄让你变胖",
        "score": 16727,
        "tag": ""
      },
      {
        "rank": 34,
        "topic": "锦月如歌热度",
        "score": 16727,
        "tag": "剧集"
      },
      {
        "rank": 35,
        "topic": "WTT横滨冠军赛2025",
        "score": 16727,
        "tag": ""
      },
      {
        "rank": 36,
        "topic": "利剑玫瑰第二季",
        "score": 16726,
        "tag": ""
      },
      {
        "rank": 37,
        "topic": "吃到腾讯芒果商战红利了",
        "score": 16725,
        "tag": "剧集"
      },
      {
        "rank": 38,
        "topic": "妻子嫂子景德镇批发式购物狂买2000元",
        "score": 16724,
        "tag": ""
      },
      {
        "rank": 39,
        "topic": "CORTIS出道曲MV",
        "score": 16724,
        "tag": "音乐"
      },
      {
        "rank": 40,
        "topic": "店主回应顾客试穿4条裤子染血渍",
        "score": 16724,
        "tag": ""
      },
      {
        "rank": 41,
        "topic": "溺亡女童左腿被回水管吸住",
        "score": 16723,
        "tag": ""
      },
      {
        "rank": 42,
        "topic": "社区盾杯",
        "score": 16723,
        "tag": ""
      },
      {
        "rank": 43,
        "topic": "抗战胜利80周年天安门演练现场",
        "score": 16722,
        "tag": ""
      },
      {
        "rank": 44,
        "topic": "百果园 钟薛高",
        "score": 16721,
        "tag": ""
      },
      {
        "rank": 45,
        "topic": "为什么叫我法拉利",
        "score": 16721,
        "tag": ""
      },
      {
        "rank": 46,
        "topic": "白桃星座一周运势",
        "score": 16720,
        "tag": ""
      },
      {
        "rank": 47,
        "topic": "韩泰山自拍",
        "score": 16720,
        "tag": ""
      },
      {
        "rank": 48,
        "topic": "26岁男子勒死73岁情人水泥埋尸",
        "score": 16719,
        "tag": ""
      },
      {
        "rank": 49,
        "topic": "AG战胜狼队",
        "score": 16718,
        "tag": ""
      },
      {
        "rank": 50,
        "topic": "2岁男童把疏通剂当玩具双手差点不保",
        "score": 16717,
        "tag": ""
      }
    ]
  },
  {
    "time": "2025/08/11 05:22:18",
    "hots": [
      {
        "rank": 0,
        "topic": "积极促进产业高端化智能化绿色化",
        "score": 0,
        "tag": "top"
      },
      {
        "rank": 1,
        "topic": "男子嫌太吵向楼下烧烤店泼不明液体",
        "score": 131550,
        "tag": ""
      },
      {
        "rank": 2,
        "topic": "男子偷580斤西瓜都吃光",
        "score": 74261,
        "tag": ""
      },
      {
        "rank": 3,
        "topic": "来天津感受河海津韵",
        "score": 58139,
        "tag": ""
      },
      {
        "rank": 4,
        "topic": "全球首个孕育机器人预计一年内面世",
        "score": 55836,
        "tag": ""
      },
      {
        "rank": 5,
        "topic": "店员回应男子误将660万彩票洗成渣",
        "score": 49557,
        "tag": ""
      },
      {
        "rank": 6,
        "topic": "蔡徐坤 Jasmine",
        "score": 36677,
        "tag": "音乐"
      },
      {
        "rank": 7,
        "topic": "婚内强奸案男方姐姐发声",
        "score": 35689,
        "tag": ""
      },
      {
        "rank": 8,
        "topic": "陶白白前妻称如果为了钱就不会离婚",
        "score": 33436,
        "tag": ""
      },
      {
        "rank": 9,
        "topic": "展轩空降",
        "score": 31772,
        "tag": ""
      },
      {
        "rank": 10,
        "topic": "社保新规对打工人有何影响",
        "score": 31284,
        "tag": ""
      },
      {
        "rank": 11,
        "topic": "张本智和不满王皓握手敷衍",
        "score": 31257,
        "tag": ""
      },
      {
        "rank": 12,
        "topic": "拉宏桑妈妈怀孕后还吃了打虫药",
        "score": 30666,
        "tag": "综艺"
      },
      {
        "rank": 13,
        "topic": "土耳其6.3级地震",
        "score": 30623,
        "tag": ""
      },
      {
        "rank": 14,
        "topic": "女子看演出时遭猥亵嫌疑人被刑拘",
        "score": 30272,
        "tag": ""
      },
      {
        "rank": 15,
        "topic": "幼童爬到13层阳台外悬空玩引体向上",
        "score": 26919,
        "tag": ""
      },
      {
        "rank": 16,
        "topic": "曝孙亦航恋情",
        "score": 24102,
        "tag": ""
      },
      {
        "rank": 17,
        "topic": "张本智和回应告状",
        "score": 23479,
        "tag": ""
      },
      {
        "rank": 18,
        "topic": "向往的生活8",
        "score": 21505,
        "tag": "综艺"
      },
      {
        "rank": 19,
        "topic": "地球超新鲜",
        "score": 20945,
        "tag": "综艺"
      },
      {
        "rank": 20,
        "topic": "逆水寒",
        "score": 20607,
        "tag": ""
      },
      {
        "rank": 21,
        "topic": "张晋和蔡少芬国外旅行突发心脏病",
        "score": 19939,
        "tag": "综艺"
      },
      {
        "rank": 22,
        "topic": "女子试穿4条裤子留下血渍赔50元",
        "score": 19152,
        "tag": ""
      },
      {
        "rank": 23,
        "topic": "妻子嫂子景德镇批发式购物狂买2000元",
        "score": 18870,
        "tag": ""
      },
      {
        "rank": 24,
        "topic": "建议多囊还是不要参与外卖大战了",
        "score": 18327,
        "tag": ""
      },
      {
        "rank": 25,
        "topic": "孙颖莎说今天回去要多吃一点",
        "score": 18027,
        "tag": ""
      },
      {
        "rank": 26,
        "topic": "办252桌婚宴后拒付52万当事方发声",
        "score": 17937,
        "tag": ""
      },
      {
        "rank": 27,
        "topic": "这不是复制粘贴这是中国军人",
        "score": 17729,
        "tag": ""
      },
      {
        "rank": 28,
        "topic": "浪浪山小妖怪",
        "score": 17642,
        "tag": "电影"
      },
      {
        "rank": 29,
        "topic": "网友票选可以出道的星二代",
        "score": 17632,
        "tag": ""
      },
      {
        "rank": 30,
        "topic": "虞书欣机场私服好健康的美",
        "score": 17626,
        "tag": ""
      },
      {
        "rank": 31,
        "topic": "杭州警方通报某演出场所发生猥亵事件",
        "score": 17625,
        "tag": ""
      },
      {
        "rank": 32,
        "topic": "店主回应顾客试穿4条裤子染血渍",
        "score": 17625,
        "tag": ""
      },
      {
        "rank": 33,
        "topic": "WTT横滨冠军赛2025",
        "score": 17625,
        "tag": ""
      },
      {
        "rank": 34,
        "topic": "你的提神饮料正悄悄让你变胖",
        "score": 17623,
        "tag": ""
      },
      {
        "rank": 35,
        "topic": "百果园 钟薛高",
        "score": 17623,
        "tag": ""
      },
      {
        "rank": 36,
        "topic": "锦月如歌热度",
        "score": 17621,
        "tag": "剧集"
      },
      {
        "rank": 37,
        "topic": "于正说赵露思很好",
        "score": 17620,
        "tag": ""
      },
      {
        "rank": 38,
        "topic": "溺亡女童左腿被回水管吸住",
        "score": 17620,
        "tag": ""
      },
      {
        "rank": 39,
        "topic": "26岁男子勒死73岁情人水泥埋尸",
        "score": 17620,
        "tag": ""
      },
      {
        "rank": 40,
        "topic": "利剑玫瑰第二季",
        "score": 17619,
        "tag": ""
      },
      {
        "rank": 41,
        "topic": "为什么叫我法拉利",
        "score": 17618,
        "tag": ""
      },
      {
        "rank": 42,
        "topic": "抗战胜利80周年天安门演练现场",
        "score": 17617,
        "tag": ""
      },
      {
        "rank": 43,
        "topic": "吃到腾讯芒果商战红利了",
        "score": 17615,
        "tag": "剧集"
      },
      {
        "rank": 44,
        "topic": "白桃星座一周运势",
        "score": 17615,
        "tag": ""
      },
      {
        "rank": 45,
        "topic": "2岁男童把疏通剂当玩具双手差点不保",
        "score": 17613,
        "tag": ""
      },
      {
        "rank": 46,
        "topic": "贺峻霖甜椒撕拉片",
        "score": 17612,
        "tag": ""
      },
      {
        "rank": 47,
        "topic": "韩泰山自拍",
        "score": 17611,
        "tag": ""
      },
      {
        "rank": 48,
        "topic": "谢霆锋杭州演唱会",
        "score": 17610,
        "tag": "演出"
      },
      {
        "rank": 49,
        "topic": "社区盾杯",
        "score": 17610,
        "tag": ""
      },
      {
        "rank": 50,
        "topic": "AG战胜狼队",
        "score": 17609,
        "tag": ""
      }
    ]
  },
  {
    "time": "2025/08/11 06:23:08",
    "hots": [
      {
        "rank": 0,
        "topic": "积极促进产业高端化智能化绿色化",
        "score": 0,
        "tag": "top"
      },
      {
        "rank": 1,
        "topic": "男子嫌太吵向楼下烧烤店泼不明液体",
        "score": 385292,
        "tag": ""
      },
      {
        "rank": 2,
        "topic": "男子偷580斤西瓜都吃光",
        "score": 152303,
        "tag": ""
      },
      {
        "rank": 3,
        "topic": "来天津感受河海津韵",
        "score": 142988,
        "tag": ""
      },
      {
        "rank": 4,
        "topic": "全球首个孕育机器人预计一年内面世",
        "score": 134383,
        "tag": ""
      },
      {
        "rank": 5,
        "topic": "陶白白前妻称如果为了钱就不会离婚",
        "score": 95892,
        "tag": ""
      },
      {
        "rank": 6,
        "topic": "店员回应男子误将660万彩票洗成渣",
        "score": 86647,
        "tag": ""
      },
      {
        "rank": 7,
        "topic": "婚内强奸案男方姐姐发声",
        "score": 76435,
        "tag": ""
      },
      {
        "rank": 8,
        "topic": "社保新规对打工人有何影响",
        "score": 64667,
        "tag": ""
      },
      {
        "rank": 9,
        "topic": "幼童爬到13层阳台外悬空玩引体向上",
        "score": 62811,
        "tag": ""
      },
      {
        "rank": 10,
        "topic": "拉宏桑妈妈怀孕后还吃了打虫药",
        "score": 62555,
        "tag": "综艺"
      },
      {
        "rank": 11,
        "topic": "张本智和不满王皓握手敷衍",
        "score": 59990,
        "tag": ""
      },
      {
        "rank": 12,
        "topic": "女子看演出时遭猥亵嫌疑人被刑拘",
        "score": 56552,
        "tag": ""
      },
      {
        "rank": 13,
        "topic": "女子试穿4条裤子留下血渍赔50元",
        "score": 51359,
        "tag": ""
      },
      {
        "rank": 14,
        "topic": "展轩空降",
        "score": 43789,
        "tag": ""
      },
      {
        "rank": 15,
        "topic": "土耳其6.3级地震",
        "score": 43442,
        "tag": ""
      },
      {
        "rank": 16,
        "topic": "张本智和回应告状",
        "score": 43442,
        "tag": ""
      },
      {
        "rank": 17,
        "topic": "藏海传韩国首张海报公开",
        "score": 39203,
        "tag": "剧集"
      },
      {
        "rank": 18,
        "topic": "妻子嫂子景德镇批发式购物狂买2000元",
        "score": 39050,
        "tag": ""
      },
      {
        "rank": 19,
        "topic": "向往的生活8",
        "score": 37429,
        "tag": "综艺"
      },
      {
        "rank": 20,
        "topic": "蔡徐坤 Jasmine",
        "score": 32337,
        "tag": "音乐"
      },
      {
        "rank": 21,
        "topic": "张晋和蔡少芬国外旅行突发心脏病",
        "score": 32080,
        "tag": "综艺"
      },
      {
        "rank": 22,
        "topic": "办252桌婚宴后拒付52万当事方发声",
        "score": 31809,
        "tag": ""
      },
      {
        "rank": 23,
        "topic": "WTT横滨冠军赛2025",
        "score": 31517,
        "tag": ""
      },
      {
        "rank": 24,
        "topic": "建议多囊还是不要参与外卖大战了",
        "score": 30802,
        "tag": ""
      },
      {
        "rank": 25,
        "topic": "杭州警方通报某演出场所发生猥亵事件",
        "score": 30392,
        "tag": ""
      },
      {
        "rank": 26,
        "topic": "曝孙亦航恋情",
        "score": 30250,
        "tag": ""
      },
      {
        "rank": 27,
        "topic": "这不是复制粘贴这是中国军人",
        "score": 29131,
        "tag": ""
      },
      {
        "rank": 28,
        "topic": "浪浪山小妖怪",
        "score": 28183,
        "tag": "电影"
      },
      {
        "rank": 29,
        "topic": "吃到腾讯芒果商战红利了",
        "score": 26859,
        "tag": "剧集"
      },
      {
        "rank": 30,
        "topic": "26岁男子勒死73岁情人水泥埋尸",
        "score": 25994,
        "tag": ""
      },
      {
        "rank": 31,
        "topic": "孙颖莎说今天回去要多吃一点",
        "score": 25946,
        "tag": ""
      },
      {
        "rank": 32,
        "topic": "溺亡女童左腿被回水管吸住",
        "score": 25864,
        "tag": ""
      },
      {
        "rank": 33,
        "topic": "百果园 钟薛高",
        "score": 25191,
        "tag": ""
      },
      {
        "rank": 34,
        "topic": "地球超新鲜",
        "score": 24260,
        "tag": "综艺"
      },
      {
        "rank": 35,
        "topic": "利剑玫瑰第二季",
        "score": 24241,
        "tag": ""
      },
      {
        "rank": 36,
        "topic": "2岁男童把疏通剂当玩具双手差点不保",
        "score": 24032,
        "tag": ""
      },
      {
        "rank": 37,
        "topic": "网友票选可以出道的星二代",
        "score": 23854,
        "tag": ""
      },
      {
        "rank": 38,
        "topic": "你的提神饮料正悄悄让你变胖",
        "score": 23574,
        "tag": ""
      },
      {
        "rank": 39,
        "topic": "抗战胜利80周年天安门演练现场",
        "score": 23573,
        "tag": ""
      },
      {
        "rank": 40,
        "topic": "为什么叫我法拉利",
        "score": 23573,
        "tag": ""
      },
      {
        "rank": 41,
        "topic": "于正说赵露思很好",
        "score": 23572,
        "tag": ""
      },
      {
        "rank": 42,
        "topic": "锦月如歌热度",
        "score": 23570,
        "tag": "剧集"
      },
      {
        "rank": 43,
        "topic": "贺峻霖甜椒撕拉片",
        "score": 23570,
        "tag": ""
      },
      {
        "rank": 44,
        "topic": "虞书欣机场私服好健康的美",
        "score": 23569,
        "tag": ""
      },
      {
        "rank": 45,
        "topic": "白桃星座一周运势",
        "score": 23568,
        "tag": ""
      },
      {
        "rank": 46,
        "topic": "社区盾杯",
        "score": 23568,
        "tag": ""
      },
      {
        "rank": 47,
        "topic": "逆水寒",
        "score": 23567,
        "tag": ""
      },
      {
        "rank": 48,
        "topic": "早餐摄入低碳水全天血糖都稳住",
        "score": 23566,
        "tag": ""
      },
      {
        "rank": 49,
        "topic": "百果园回应加盟店数量锐减",
        "score": 23564,
        "tag": ""
      },
      {
        "rank": 50,
        "topic": "店主回应顾客试穿4条裤子染血渍",
        "score": 23564,
        "tag": ""
      }
    ]
  },
  {
    "time": "2025/08/11 07:23:19",
    "hots": [
      {
        "rank": 0,
        "topic": "积极促进产业高端化智能化绿色化",
        "score": 0,
        "tag": "top"
      },
      {
        "rank": 1,
        "topic": "男子嫌太吵向楼下烧烤店泼不明液体",
        "score": 801468,
        "tag": ""
      },
      {
        "rank": 2,
        "topic": "全球首个孕育机器人预计一年内面世",
        "score": 353733,
        "tag": ""
      },
      {
        "rank": 3,
        "topic": "来天津感受河海津韵",
        "score": 332773,
        "tag": ""
      },
      {
        "rank": 4,
        "topic": "男子偷580斤西瓜都吃光",
        "score": 321985,
        "tag": ""
      },
      {
        "rank": 5,
        "topic": "陶白白前妻称如果为了钱就不会离婚",
        "score": 226634,
        "tag": ""
      },
      {
        "rank": 6,
        "topic": "店员回应男子误将660万彩票洗成渣",
        "score": 211824,
        "tag": ""
      },
      {
        "rank": 7,
        "topic": "婚内强奸案男方姐姐发声",
        "score": 198711,
        "tag": ""
      },
      {
        "rank": 8,
        "topic": "社保新规对打工人有何影响",
        "score": 168408,
        "tag": ""
      },
      {
        "rank": 9,
        "topic": "向往的生活8",
        "score": 161767,
        "tag": "综艺"
      },
      {
        "rank": 10,
        "topic": "商家称外卖大战月亏超万元",
        "score": 156214,
        "tag": ""
      },
      {
        "rank": 11,
        "topic": "张本智和取关早田希娜",
        "score": 148768,
        "tag": ""
      },
      {
        "rank": 12,
        "topic": "张本智和不满王皓握手敷衍",
        "score": 141350,
        "tag": ""
      },
      {
        "rank": 13,
        "topic": "女子看演出时遭猥亵嫌疑人被刑拘",
        "score": 135005,
        "tag": ""
      },
      {
        "rank": 14,
        "topic": "幼童爬到13层阳台外悬空玩引体向上",
        "score": 131568,
        "tag": ""
      },
      {
        "rank": 15,
        "topic": "土耳其6.3级地震",
        "score": 111964,
        "tag": ""
      },
      {
        "rank": 16,
        "topic": "妻子嫂子景德镇批发式购物狂买2000元",
        "score": 109521,
        "tag": ""
      },
      {
        "rank": 17,
        "topic": "藏海传韩国首张海报公开",
        "score": 106753,
        "tag": "剧集"
      },
      {
        "rank": 18,
        "topic": "浪浪山小妖怪",
        "score": 105188,
        "tag": "电影"
      },
      {
        "rank": 19,
        "topic": "陈奕迅",
        "score": 101736,
        "tag": "演出"
      },
      {
        "rank": 20,
        "topic": "展轩空降",
        "score": 99844,
        "tag": ""
      },
      {
        "rank": 21,
        "topic": "张本智和回应告状",
        "score": 97106,
        "tag": ""
      },
      {
        "rank": 22,
        "topic": "办252桌婚宴后拒付52万当事方发声",
        "score": 96001,
        "tag": ""
      },
      {
        "rank": 23,
        "topic": "张晋和蔡少芬国外旅行突发心脏病",
        "score": 95604,
        "tag": "综艺"
      },
      {
        "rank": 24,
        "topic": "百果园 钟薛高",
        "score": 75839,
        "tag": ""
      },
      {
        "rank": 25,
        "topic": "溺亡女童左腿被回水管吸住",
        "score": 67336,
        "tag": ""
      },
      {
        "rank": 26,
        "topic": "曝孙亦航恋情",
        "score": 65093,
        "tag": ""
      },
      {
        "rank": 27,
        "topic": "感到疲惫要主动扔掉这2样东西",
        "score": 64314,
        "tag": ""
      },
      {
        "rank": 28,
        "topic": "网友票选可以出道的星二代",
        "score": 63644,
        "tag": ""
      },
      {
        "rank": 29,
        "topic": "早餐摄入低碳水全天血糖都稳住",
        "score": 63535,
        "tag": ""
      },
      {
        "rank": 30,
        "topic": "利剑玫瑰第二季",
        "score": 59910,
        "tag": ""
      },
      {
        "rank": 31,
        "topic": "这不是复制粘贴这是中国军人",
        "score": 57945,
        "tag": ""
      },
      {
        "rank": 32,
        "topic": "为什么叫我法拉利",
        "score": 55993,
        "tag": ""
      },
      {
        "rank": 33,
        "topic": "26岁男子勒死73岁情人水泥埋尸",
        "score": 54589,
        "tag": ""
      },
      {
        "rank": 34,
        "topic": "杭州警方通报某演出场所发生猥亵事件",
        "score": 51793,
        "tag": ""
      },
      {
        "rank": 35,
        "topic": "WTT横滨冠军赛2025",
        "score": 49370,
        "tag": ""
      },
      {
        "rank": 36,
        "topic": "蔡徐坤 Jasmine",
        "score": 47284,
        "tag": "音乐"
      },
      {
        "rank": 37,
        "topic": "2岁男童把疏通剂当玩具双手差点不保",
        "score": 45089,
        "tag": ""
      },
      {
        "rank": 38,
        "topic": "巴代表问以色列为何还能安坐联合国",
        "score": 44422,
        "tag": ""
      },
      {
        "rank": 39,
        "topic": "于正说赵露思很好",
        "score": 43983,
        "tag": ""
      },
      {
        "rank": 40,
        "topic": "抗战胜利80周年天安门演练现场",
        "score": 43694,
        "tag": ""
      },
      {
        "rank": 41,
        "topic": "锦月如歌热度",
        "score": 42868,
        "tag": "剧集"
      },
      {
        "rank": 42,
        "topic": "土耳其6.3级地震1死29伤",
        "score": 41768,
        "tag": ""
      },
      {
        "rank": 43,
        "topic": "孙颖莎说今天回去要多吃一点",
        "score": 41646,
        "tag": ""
      },
      {
        "rank": 44,
        "topic": "拉宏桑妈妈怀孕后还吃了打虫药",
        "score": 40703,
        "tag": "综艺"
      },
      {
        "rank": 45,
        "topic": "女子试穿4条裤子留下血渍赔50元",
        "score": 39597,
        "tag": ""
      },
      {
        "rank": 46,
        "topic": "虞书欣机场私服好健康的美",
        "score": 38223,
        "tag": ""
      },
      {
        "rank": 47,
        "topic": "白桃星座一周运势",
        "score": 38079,
        "tag": ""
      },
      {
        "rank": 48,
        "topic": "建议多囊还是不要参与外卖大战了",
        "score": 37476,
        "tag": ""
      },
      {
        "rank": 49,
        "topic": "你的提神饮料正悄悄让你变胖",
        "score": 37466,
        "tag": ""
      },
      {
        "rank": 50,
        "topic": "贺峻霖甜椒撕拉片",
        "score": 37452,
        "tag": ""
      }
    ]
  },
  {
    "time": "2025/08/11 10:09:12",
    "hots": [
      {
        "rank": 0,
        "topic": "积极促进产业高端化智能化绿色化",
        "score": 0,
        "tag": "top"
      },
      {
        "rank": 1,
        "topic": "日本麦当劳乱象",
        "score": 1166536,
        "tag": ""
      },
      {
        "rank": 2,
        "topic": "麦琳称录完再见爱人过得不好",
        "score": 1033170,
        "tag": "综艺"
      },
      {
        "rank": 3,
        "topic": "来天津感受河海津韵",
        "score": 468107,
        "tag": ""
      },
      {
        "rank": 4,
        "topic": "演唱会迟到被汪苏泷抓个正着",
        "score": 449987,
        "tag": "演出"
      },
      {
        "rank": 5,
        "topic": "墨镜大爷救人后又被一群人救了",
        "score": 421947,
        "tag": ""
      },
      {
        "rank": 6,
        "topic": "全球首个孕育机器人预计一年内面世",
        "score": 410326,
        "tag": ""
      },
      {
        "rank": 7,
        "topic": "电视剧无可替代开机",
        "score": 408518,
        "tag": ""
      },
      {
        "rank": 8,
        "topic": "男子偷580斤西瓜都吃光",
        "score": 359769,
        "tag": ""
      },
      {
        "rank": 9,
        "topic": "孙颖莎vs石洵瑶",
        "score": 316878,
        "tag": ""
      },
      {
        "rank": 10,
        "topic": "泡泡玛特泰国店被指撞脸名创优品",
        "score": 316691,
        "tag": ""
      },
      {
        "rank": 11,
        "topic": "在美中国古籍被华裔掉包带出",
        "score": 309660,
        "tag": ""
      },
      {
        "rank": 12,
        "topic": "陶白白回应疑似鹿角新恋情",
        "score": 308702,
        "tag": ""
      },
      {
        "rank": 13,
        "topic": "张本智和取关早田希娜",
        "score": 303339,
        "tag": ""
      },
      {
        "rank": 14,
        "topic": "早春晴朗 开机",
        "score": 301616,
        "tag": ""
      },
      {
        "rank": 15,
        "topic": "迪丽热巴 VOGUE金九",
        "score": 248890,
        "tag": ""
      },
      {
        "rank": 16,
        "topic": "婚内强奸案男方姐姐发声",
        "score": 241922,
        "tag": ""
      },
      {
        "rank": 17,
        "topic": "子夜归",
        "score": 235132,
        "tag": "剧集"
      },
      {
        "rank": 18,
        "topic": "男子嫌太吵向楼下烧烤店泼不明液体",
        "score": 197738,
        "tag": ""
      },
      {
        "rank": 19,
        "topic": "商家称外卖大战月亏超万元",
        "score": 165489,
        "tag": ""
      },
      {
        "rank": 20,
        "topic": "日照爷爷每周带孙子坐4小时车到青岛",
        "score": 157615,
        "tag": ""
      },
      {
        "rank": 21,
        "topic": "日本前国脚为否认南京大屠杀道歉",
        "score": 157207,
        "tag": ""
      },
      {
        "rank": 22,
        "topic": "鹿角现任",
        "score": 148651,
        "tag": ""
      },
      {
        "rank": 23,
        "topic": "毕雯珺怒斥代拍",
        "score": 147133,
        "tag": ""
      },
      {
        "rank": 24,
        "topic": "社保新规对打工人有何影响",
        "score": 145134,
        "tag": ""
      },
      {
        "rank": 25,
        "topic": "陈乔恩说上镜胖3斤",
        "score": 142831,
        "tag": ""
      },
      {
        "rank": 26,
        "topic": "只有考过驾照的才知道她说的有多真",
        "score": 142286,
        "tag": ""
      },
      {
        "rank": 27,
        "topic": "店员回应男子误将660万彩票洗成渣",
        "score": 126474,
        "tag": ""
      },
      {
        "rank": 28,
        "topic": "邓超女儿最近迷上了卡拉ok",
        "score": 117596,
        "tag": ""
      },
      {
        "rank": 29,
        "topic": "坐月子需要100天",
        "score": 114961,
        "tag": ""
      },
      {
        "rank": 30,
        "topic": "刘诗诗爱丽儿公主",
        "score": 113521,
        "tag": ""
      },
      {
        "rank": 31,
        "topic": "小酒窝管乐旋转跳跃一下",
        "score": 112103,
        "tag": ""
      },
      {
        "rank": 32,
        "topic": "幼童爬到13层阳台外悬空玩引体向上",
        "score": 110740,
        "tag": ""
      },
      {
        "rank": 33,
        "topic": "老人走失近20小时狗狗一直陪伴左右",
        "score": 109909,
        "tag": ""
      },
      {
        "rank": 34,
        "topic": "聋猫突然看到人的反应",
        "score": 99525,
        "tag": ""
      },
      {
        "rank": 35,
        "topic": "以色列已批准占领加沙城计划",
        "score": 97710,
        "tag": ""
      },
      {
        "rank": 36,
        "topic": "孙亦航回应恋情",
        "score": 91756,
        "tag": ""
      },
      {
        "rank": 37,
        "topic": "宁德时代宜春锂云母矿准时停产",
        "score": 77707,
        "tag": ""
      },
      {
        "rank": 38,
        "topic": "浪浪山小妖怪",
        "score": 75456,
        "tag": "电影"
      },
      {
        "rank": 39,
        "topic": "胖东来回应招聘刑释人员",
        "score": 74063,
        "tag": ""
      },
      {
        "rank": 40,
        "topic": "无可替代",
        "score": 73089,
        "tag": "剧集"
      },
      {
        "rank": 41,
        "topic": "缅怀抗战先烈",
        "score": 73011,
        "tag": ""
      },
      {
        "rank": 42,
        "topic": "他在战场上牺牲时年仅32岁",
        "score": 70342,
        "tag": ""
      },
      {
        "rank": 43,
        "topic": "五条悟燃王",
        "score": 69607,
        "tag": ""
      },
      {
        "rank": 44,
        "topic": "拉宏桑妈妈怀孕后还吃了打虫药",
        "score": 65766,
        "tag": "综艺"
      },
      {
        "rank": 45,
        "topic": "藏海传韩国首张海报公开",
        "score": 65678,
        "tag": "剧集"
      },
      {
        "rank": 46,
        "topic": "早餐摄入低碳水全天血糖都稳住",
        "score": 64843,
        "tag": ""
      },
      {
        "rank": 47,
        "topic": "于正说赵露思很好",
        "score": 64438,
        "tag": ""
      },
      {
        "rank": 48,
        "topic": "燕云十六声",
        "score": 63618,
        "tag": ""
      },
      {
        "rank": 49,
        "topic": "土耳其6.3级地震",
        "score": 61969,
        "tag": ""
      },
      {
        "rank": 50,
        "topic": "九头身裁判震惊自己世运会爆火",
        "score": 58852,
        "tag": ""
      }
    ]
  },
  {
    "time": "2025/08/11 12:06:55",
    "hots": [
      {
        "rank": 0,
        "topic": "积极促进产业高端化智能化绿色化",
        "score": 0,
        "tag": "top"
      },
      {
        "rank": 1,
        "topic": "日本麦当劳乱象",
        "score": 1185576,
        "tag": ""
      },
      {
        "rank": 2,
        "topic": "4岁男孩从22楼窗台坠落",
        "score": 933422,
        "tag": ""
      },
      {
        "rank": 3,
        "topic": "来天津感受河海津韵",
        "score": 639595,
        "tag": ""
      },
      {
        "rank": 4,
        "topic": "赵今麦领衔主演无可替代",
        "score": 630282,
        "tag": "剧集"
      },
      {
        "rank": 5,
        "topic": "女子单手骑车摔倒数米外车主担次责",
        "score": 576438,
        "tag": ""
      },
      {
        "rank": 6,
        "topic": "深圳回应非婚生育不能领育儿补贴",
        "score": 401558,
        "tag": ""
      },
      {
        "rank": 7,
        "topic": "女子遛狗未拴绳被轧后失控发飙",
        "score": 387011,
        "tag": ""
      },
      {
        "rank": 8,
        "topic": "麦琳称录完再见爱人过得不好",
        "score": 380417,
        "tag": "综艺"
      },
      {
        "rank": 9,
        "topic": "上海医保",
        "score": 357759,
        "tag": ""
      },
      {
        "rank": 10,
        "topic": "张本智和vs贾哈",
        "score": 345878,
        "tag": ""
      },
      {
        "rank": 11,
        "topic": "黄子韬徐艺洋婚礼能看到EXO合体吗",
        "score": 340403,
        "tag": ""
      },
      {
        "rank": 12,
        "topic": "周华健肚子",
        "score": 338415,
        "tag": "演出"
      },
      {
        "rank": 13,
        "topic": "虞书欣这个比例绝了",
        "score": 333746,
        "tag": ""
      },
      {
        "rank": 14,
        "topic": "蛟龙行动",
        "score": 325666,
        "tag": "电影"
      },
      {
        "rank": 15,
        "topic": "迪丽热巴 VOGUE金九",
        "score": 282090,
        "tag": ""
      },
      {
        "rank": 16,
        "topic": "CPB檀健次",
        "score": 252596,
        "tag": ""
      },
      {
        "rank": 17,
        "topic": "献鱼定档",
        "score": 247320,
        "tag": "剧集"
      },
      {
        "rank": 18,
        "topic": "当一个人朋友圈不再更新",
        "score": 245052,
        "tag": ""
      },
      {
        "rank": 19,
        "topic": "王一博正式确诊为赛博红牛",
        "score": 229222,
        "tag": ""
      },
      {
        "rank": 20,
        "topic": "4次断骨打开180度折叠男孩近况",
        "score": 220880,
        "tag": ""
      },
      {
        "rank": 21,
        "topic": "生理性厌恶的7个躯体信号",
        "score": 217401,
        "tag": ""
      },
      {
        "rank": 22,
        "topic": "车主回应女子5米外摔倒自己负次责",
        "score": 210566,
        "tag": ""
      },
      {
        "rank": 23,
        "topic": "张本智和 谁教你的庆祝动作",
        "score": 210510,
        "tag": ""
      },
      {
        "rank": 24,
        "topic": "墨镜大爷救人后又被一群人救了",
        "score": 206906,
        "tag": ""
      },
      {
        "rank": 25,
        "topic": "人生总该有台四驱车",
        "score": 197226,
        "tag": ""
      },
      {
        "rank": 26,
        "topic": "日本前国脚为否认南京大屠杀道歉",
        "score": 195529,
        "tag": ""
      },
      {
        "rank": 27,
        "topic": "三人行先导预告片",
        "score": 195508,
        "tag": ""
      },
      {
        "rank": 28,
        "topic": "单依纯永不失联的爱一张嘴就哭了",
        "score": 195145,
        "tag": "演出"
      },
      {
        "rank": 29,
        "topic": "60岁张卫健在演唱会上掏出老年卡",
        "score": 195005,
        "tag": "演出"
      },
      {
        "rank": 30,
        "topic": "夕阳红公寓非法集资28亿爆雷后续",
        "score": 194889,
        "tag": ""
      },
      {
        "rank": 31,
        "topic": "全球首个孕育机器人预计一年内面世",
        "score": 194695,
        "tag": ""
      },
      {
        "rank": 32,
        "topic": "张本智和4比1贾哈",
        "score": 163955,
        "tag": ""
      },
      {
        "rank": 33,
        "topic": "张本智和取关早田希娜",
        "score": 161283,
        "tag": ""
      },
      {
        "rank": 34,
        "topic": "独居日本女子家中发现陌生甲片",
        "score": 160205,
        "tag": ""
      },
      {
        "rank": 35,
        "topic": "带你看清武大图书馆事件每个细节",
        "score": 158422,
        "tag": ""
      },
      {
        "rank": 36,
        "topic": "台风杨柳最强可达台风级",
        "score": 156384,
        "tag": ""
      },
      {
        "rank": 37,
        "topic": "没有文化已经当不了杀手了",
        "score": 152582,
        "tag": ""
      },
      {
        "rank": 38,
        "topic": "孙颖莎vs石洵瑶",
        "score": 150560,
        "tag": ""
      },
      {
        "rank": 39,
        "topic": "睡姿 焦虑",
        "score": 149356,
        "tag": ""
      },
      {
        "rank": 40,
        "topic": "赵露思说内娱谁不羡慕我粉丝",
        "score": 149297,
        "tag": ""
      },
      {
        "rank": 41,
        "topic": "子夜归献鱼同期开播",
        "score": 149179,
        "tag": "剧集"
      },
      {
        "rank": 42,
        "topic": "苏醒被胡夏迷的不知天地为何物了",
        "score": 148536,
        "tag": ""
      },
      {
        "rank": 43,
        "topic": "最希望李承铉被披哥淘汰的人是Lucky",
        "score": 141888,
        "tag": "综艺"
      },
      {
        "rank": 44,
        "topic": "剑网3",
        "score": 139167,
        "tag": ""
      },
      {
        "rank": 45,
        "topic": "BLACKPINK将11月发行新专",
        "score": 134511,
        "tag": "音乐"
      },
      {
        "rank": 46,
        "topic": "陶白白回应疑似鹿角新恋情",
        "score": 134174,
        "tag": ""
      },
      {
        "rank": 47,
        "topic": "湖北暴雨大暴雨特大暴雨来了",
        "score": 127465,
        "tag": ""
      },
      {
        "rank": 48,
        "topic": "环球时报专访朱一龙",
        "score": 125877,
        "tag": "电影"
      },
      {
        "rank": 49,
        "topic": "男子偷580斤西瓜都吃光",
        "score": 116876,
        "tag": ""
      },
      {
        "rank": 50,
        "topic": "长大是你突然觉得好困",
        "score": 115762,
        "tag": ""
      }
    ]
  },
  {
    "time": "2025/08/11 13:31:58",
    "hots": [
      {
        "rank": 0,
        "topic": "以文化人以文兴业",
        "score": 0,
        "tag": "top"
      },
      {
        "rank": 1,
        "topic": "王楚钦vs莫雷加德",
        "score": 1158969,
        "tag": ""
      },
      {
        "rank": 2,
        "topic": "撒贝宁保送北大的真实原因",
        "score": 653473,
        "tag": "综艺"
      },
      {
        "rank": 3,
        "topic": "抗战胜利80周年天安门演练现场",
        "score": 620156,
        "tag": ""
      },
      {
        "rank": 4,
        "topic": "女子为避雨进彩票店顺手刮中100万",
        "score": 590083,
        "tag": ""
      },
      {
        "rank": 5,
        "topic": "4岁男孩从22楼窗台坠落",
        "score": 572899,
        "tag": ""
      },
      {
        "rank": 6,
        "topic": "日本麦当劳乱象",
        "score": 473435,
        "tag": ""
      },
      {
        "rank": 7,
        "topic": "张本智和 谁教你的庆祝动作",
        "score": 471676,
        "tag": ""
      },
      {
        "rank": 8,
        "topic": "深圳回应非婚生育不能领育儿补贴",
        "score": 418772,
        "tag": ""
      },
      {
        "rank": 9,
        "topic": "沈阳一企业洗手液原料进入河道",
        "score": 414078,
        "tag": ""
      },
      {
        "rank": 10,
        "topic": "蒋欣像冷宫疯掉的妃子",
        "score": 413278,
        "tag": ""
      },
      {
        "rank": 11,
        "topic": "鹿晗关晓彤同款挂件",
        "score": 407918,
        "tag": ""
      },
      {
        "rank": 12,
        "topic": "黄子韬徐艺洋婚礼能看到EXO合体吗",
        "score": 399682,
        "tag": ""
      },
      {
        "rank": 13,
        "topic": "当一个人朋友圈不再更新",
        "score": 395073,
        "tag": ""
      },
      {
        "rank": 14,
        "topic": "贾哈教练与张本智和热情握手",
        "score": 391823,
        "tag": ""
      },
      {
        "rank": 15,
        "topic": "王楚钦4比0莫雷加德",
        "score": 327066,
        "tag": ""
      },
      {
        "rank": 16,
        "topic": "陶白白前妻和现任分手",
        "score": 297753,
        "tag": ""
      },
      {
        "rank": 17,
        "topic": "王楚钦孙颖莎领衔冲冠",
        "score": 246625,
        "tag": ""
      },
      {
        "rank": 18,
        "topic": "邢菲说杨幂帮她走出原生家庭困境",
        "score": 231314,
        "tag": "剧集"
      },
      {
        "rank": 19,
        "topic": "4次断骨打开180度折叠男孩近况",
        "score": 226929,
        "tag": ""
      },
      {
        "rank": 20,
        "topic": "麦琳称录完再见爱人过得不好",
        "score": 219966,
        "tag": "综艺"
      },
      {
        "rank": 21,
        "topic": "生理性厌恶的7个躯体信号",
        "score": 219490,
        "tag": ""
      },
      {
        "rank": 22,
        "topic": "睡姿 焦虑",
        "score": 217635,
        "tag": ""
      },
      {
        "rank": 23,
        "topic": "女子单手骑车摔倒数米外车主担次责",
        "score": 213883,
        "tag": ""
      },
      {
        "rank": 24,
        "topic": "王楚钦11比1莫雷加德",
        "score": 199892,
        "tag": ""
      },
      {
        "rank": 25,
        "topic": "CPB檀健次",
        "score": 199205,
        "tag": ""
      },
      {
        "rank": 26,
        "topic": "王楚钦11比4莫雷加德",
        "score": 198956,
        "tag": ""
      },
      {
        "rank": 27,
        "topic": "上海医保",
        "score": 189105,
        "tag": ""
      },
      {
        "rank": 28,
        "topic": "心动的信号8",
        "score": 186723,
        "tag": "综艺"
      },
      {
        "rank": 29,
        "topic": "赵今麦领衔主演无可替代",
        "score": 186501,
        "tag": "剧集"
      },
      {
        "rank": 30,
        "topic": "以色列已批准占领加沙城计划",
        "score": 186416,
        "tag": ""
      },
      {
        "rank": 31,
        "topic": "虞书欣这个比例绝了",
        "score": 186415,
        "tag": ""
      },
      {
        "rank": 32,
        "topic": "盛世天下定档9月",
        "score": 165229,
        "tag": ""
      },
      {
        "rank": 33,
        "topic": "日本扇耳光餐厅",
        "score": 155498,
        "tag": ""
      },
      {
        "rank": 34,
        "topic": "王楚钦强势晋级决赛",
        "score": 148715,
        "tag": ""
      },
      {
        "rank": 35,
        "topic": "鹿角 以后我会擦亮眼睛",
        "score": 148313,
        "tag": ""
      },
      {
        "rank": 36,
        "topic": "周华健肚子",
        "score": 144062,
        "tag": "演出"
      },
      {
        "rank": 37,
        "topic": "事业单位面试邪修大佬在民间",
        "score": 128787,
        "tag": ""
      },
      {
        "rank": 38,
        "topic": "非婚生子女 育儿补贴",
        "score": 128488,
        "tag": ""
      },
      {
        "rank": 39,
        "topic": "车主回应女子5米外摔倒自己负次责",
        "score": 128425,
        "tag": ""
      },
      {
        "rank": 40,
        "topic": "巴勒斯坦男子拍下自己被枪杀瞬间",
        "score": 122412,
        "tag": ""
      },
      {
        "rank": 41,
        "topic": "湖北暴雨大暴雨特大暴雨来了",
        "score": 115379,
        "tag": ""
      },
      {
        "rank": 42,
        "topic": "王楚钦男单半决赛登场",
        "score": 113631,
        "tag": ""
      },
      {
        "rank": 43,
        "topic": "俩男一女拉扯这45秒好刺激",
        "score": 112876,
        "tag": ""
      },
      {
        "rank": 44,
        "topic": "魏大勋智性恋天菜",
        "score": 112227,
        "tag": ""
      },
      {
        "rank": 45,
        "topic": "迪丽热巴 VOGUE金九",
        "score": 109133,
        "tag": ""
      },
      {
        "rank": 46,
        "topic": "A股",
        "score": 102305,
        "tag": ""
      },
      {
        "rank": 47,
        "topic": "花4小时从杭州到长沙过周末",
        "score": 101995,
        "tag": ""
      },
      {
        "rank": 48,
        "topic": "孙颖莎陈幸同横滨争冠",
        "score": 99343,
        "tag": ""
      },
      {
        "rank": 49,
        "topic": "谢霆锋巡演Tshirt是和儿子一起画的",
        "score": 98953,
        "tag": "演出"
      },
      {
        "rank": 50,
        "topic": "鬼吹灯有动画版了",
        "score": 98656,
        "tag": ""
      }
    ]
  },
  {
    "time": "2025/08/11 14:40:08",
    "hots": [
      {
        "rank": 0,
        "topic": "以文化人以文兴业",
        "score": 0,
        "tag": "top"
      },
      {
        "rank": 1,
        "topic": "女子为避雨进彩票店顺手刮中100万",
        "score": 1094564,
        "tag": ""
      },
      {
        "rank": 2,
        "topic": "非婚生子女 育儿补贴",
        "score": 516121,
        "tag": ""
      },
      {
        "rank": 3,
        "topic": "抗战胜利80周年天安门演练现场",
        "score": 358394,
        "tag": ""
      },
      {
        "rank": 4,
        "topic": "日本麦当劳乱象",
        "score": 325580,
        "tag": ""
      },
      {
        "rank": 5,
        "topic": "高亚麟被执行310万",
        "score": 312118,
        "tag": ""
      },
      {
        "rank": 6,
        "topic": "撒贝宁保送北大的真实原因",
        "score": 297356,
        "tag": "综艺"
      },
      {
        "rank": 7,
        "topic": "中国好声音选手朴翔去世",
        "score": 283733,
        "tag": ""
      },
      {
        "rank": 8,
        "topic": "王楚钦4比0莫雷加德",
        "score": 282708,
        "tag": ""
      },
      {
        "rank": 9,
        "topic": "蒋欣像冷宫疯掉的妃子",
        "score": 257162,
        "tag": ""
      },
      {
        "rank": 10,
        "topic": "外甥拦门致舅妈情夫跳楼伤残赔18.5万",
        "score": 248132,
        "tag": ""
      },
      {
        "rank": 11,
        "topic": "鹿晗关晓彤同款挂件",
        "score": 247687,
        "tag": ""
      },
      {
        "rank": 12,
        "topic": "陶白白前妻和现任分手",
        "score": 245621,
        "tag": ""
      },
      {
        "rank": 13,
        "topic": "黄子韬徐艺洋婚礼能看到EXO合体吗",
        "score": 242243,
        "tag": ""
      },
      {
        "rank": 14,
        "topic": "陈思诚带儿子为佟丽娅庆生",
        "score": 240764,
        "tag": ""
      },
      {
        "rank": 15,
        "topic": "怪不得医生会反复套话",
        "score": 239600,
        "tag": ""
      },
      {
        "rank": 16,
        "topic": "第一次见粉丝塌房",
        "score": 237039,
        "tag": ""
      },
      {
        "rank": 17,
        "topic": "当一个人朋友圈不再更新",
        "score": 236333,
        "tag": ""
      },
      {
        "rank": 18,
        "topic": "分手尽量安排在周末",
        "score": 219927,
        "tag": ""
      },
      {
        "rank": 19,
        "topic": "围殴中国留学生的肇事者均被保释",
        "score": 213265,
        "tag": ""
      },
      {
        "rank": 20,
        "topic": "梁朝伟每一步都舒适",
        "score": 209183,
        "tag": ""
      },
      {
        "rank": 21,
        "topic": "男子陪妻子做流产发现孩子是邻居的",
        "score": 208407,
        "tag": ""
      },
      {
        "rank": 22,
        "topic": "生理性厌恶的7个躯体信号",
        "score": 208031,
        "tag": ""
      },
      {
        "rank": 23,
        "topic": "王玉雯是内娱幼教吧",
        "score": 206073,
        "tag": ""
      },
      {
        "rank": 24,
        "topic": "贾哈教练与张本智和热情握手",
        "score": 185042,
        "tag": ""
      },
      {
        "rank": 25,
        "topic": "王楚钦说等一下让我说完",
        "score": 181457,
        "tag": ""
      },
      {
        "rank": 26,
        "topic": "恋综占有欲最强的男嘉宾出现了",
        "score": 173087,
        "tag": "综艺"
      },
      {
        "rank": 27,
        "topic": "刘轩丞在艺考学校外号馒头哥",
        "score": 169565,
        "tag": ""
      },
      {
        "rank": 28,
        "topic": "中国海警依法对菲船予以驱离",
        "score": 151741,
        "tag": ""
      },
      {
        "rank": 29,
        "topic": "深圳回应非婚生育不能领育儿补贴",
        "score": 150073,
        "tag": ""
      },
      {
        "rank": 30,
        "topic": "4岁男孩从22楼窗台坠落",
        "score": 143066,
        "tag": ""
      },
      {
        "rank": 31,
        "topic": "朴彩英也给Jennie打码了",
        "score": 142564,
        "tag": ""
      },
      {
        "rank": 32,
        "topic": "乐远cp",
        "score": 133644,
        "tag": "综艺"
      },
      {
        "rank": 33,
        "topic": "宜家宣布入驻京东",
        "score": 132552,
        "tag": ""
      },
      {
        "rank": 34,
        "topic": "张本智和 谁教你的庆祝动作",
        "score": 131803,
        "tag": ""
      },
      {
        "rank": 35,
        "topic": "王楚钦vs莫雷加德",
        "score": 126100,
        "tag": ""
      },
      {
        "rank": 36,
        "topic": "虞书欣这个比例绝了",
        "score": 122721,
        "tag": ""
      },
      {
        "rank": 37,
        "topic": "王楚钦打得莫雷加德碎碎念",
        "score": 117170,
        "tag": ""
      },
      {
        "rank": 38,
        "topic": "王一博正式确诊为赛博红牛",
        "score": 115956,
        "tag": ""
      },
      {
        "rank": 39,
        "topic": "年入百万老板去假装上班公司面试",
        "score": 115834,
        "tag": ""
      },
      {
        "rank": 40,
        "topic": "东极岛",
        "score": 115739,
        "tag": ""
      },
      {
        "rank": 41,
        "topic": "微信支付 隐私保护",
        "score": 114833,
        "tag": ""
      },
      {
        "rank": 42,
        "topic": "巴勒斯坦男子拍下自己被枪杀瞬间",
        "score": 111732,
        "tag": ""
      },
      {
        "rank": 43,
        "topic": "王楚钦孙颖莎领衔冲冠",
        "score": 111613,
        "tag": ""
      },
      {
        "rank": 44,
        "topic": "第五人格",
        "score": 108428,
        "tag": ""
      },
      {
        "rank": 45,
        "topic": "权志龙演唱会大屏 为自己而活",
        "score": 106685,
        "tag": "演出"
      },
      {
        "rank": 46,
        "topic": "巴黎合伙人阵容官宣",
        "score": 106358,
        "tag": "综艺"
      },
      {
        "rank": 47,
        "topic": "上海医保",
        "score": 105378,
        "tag": ""
      },
      {
        "rank": 48,
        "topic": "事业单位面试邪修大佬在民间",
        "score": 105234,
        "tag": ""
      },
      {
        "rank": 49,
        "topic": "卖个水果何德何能搞义务教育",
        "score": 103166,
        "tag": ""
      },
      {
        "rank": 50,
        "topic": "李乃文快成浣衣局主事了",
        "score": 101190,
        "tag": "综艺"
      }
    ]
  },
  {
    "time": "2025/08/11 15:28:59",
    "hots": [
      {
        "rank": 0,
        "topic": "以文化人以文兴业",
        "score": 0,
        "tag": "top"
      },
      {
        "rank": 1,
        "topic": "中国好声音选手朴翔去世",
        "score": 1114280,
        "tag": ""
      },
      {
        "rank": 2,
        "topic": "女子为避雨进彩票店顺手刮中100万",
        "score": 463704,
        "tag": ""
      },
      {
        "rank": 3,
        "topic": "抗战胜利80周年天安门演练现场",
        "score": 318569,
        "tag": ""
      },
      {
        "rank": 4,
        "topic": "王栎鑫苏醒吵架",
        "score": 300521,
        "tag": ""
      },
      {
        "rank": 5,
        "topic": "非婚生子女 育儿补贴",
        "score": 295993,
        "tag": ""
      },
      {
        "rank": 6,
        "topic": "章凝成为VOGUE US主编",
        "score": 278466,
        "tag": ""
      },
      {
        "rank": 7,
        "topic": "朴彩英也给Jennie打码了",
        "score": 277731,
        "tag": ""
      },
      {
        "rank": 8,
        "topic": "高亚麟被执行310万",
        "score": 274848,
        "tag": ""
      },
      {
        "rank": 9,
        "topic": "黄金",
        "score": 265412,
        "tag": ""
      },
      {
        "rank": 10,
        "topic": "广西一女生考入清华被奖励100万元",
        "score": 262388,
        "tag": ""
      },
      {
        "rank": 11,
        "topic": "第一次见粉丝塌房",
        "score": 261766,
        "tag": ""
      },
      {
        "rank": 12,
        "topic": "鹿晗关晓彤同款挂件",
        "score": 255404,
        "tag": ""
      },
      {
        "rank": 13,
        "topic": "陶白白前妻和现任分手",
        "score": 249540,
        "tag": ""
      },
      {
        "rank": 14,
        "topic": "外甥拦门致舅妈情夫跳楼伤残赔18.5万",
        "score": 245699,
        "tag": ""
      },
      {
        "rank": 15,
        "topic": "怪不得医生会反复套话",
        "score": 243738,
        "tag": ""
      },
      {
        "rank": 16,
        "topic": "黄子韬徐艺洋婚礼能看到EXO合体吗",
        "score": 239590,
        "tag": ""
      },
      {
        "rank": 17,
        "topic": "陈思诚带儿子为佟丽娅庆生",
        "score": 235708,
        "tag": ""
      },
      {
        "rank": 18,
        "topic": "日本麦当劳乱象",
        "score": 231552,
        "tag": ""
      },
      {
        "rank": 19,
        "topic": "龚俊王玉雯撞睡衣了",
        "score": 224946,
        "tag": "综艺"
      },
      {
        "rank": 20,
        "topic": "卖个水果何德何能搞义务教育",
        "score": 212980,
        "tag": ""
      },
      {
        "rank": 21,
        "topic": "生理性厌恶的7个躯体信号",
        "score": 206300,
        "tag": ""
      },
      {
        "rank": 22,
        "topic": "分手尽量安排在周末",
        "score": 198213,
        "tag": ""
      },
      {
        "rank": 23,
        "topic": "刘轩丞在艺考学校外号馒头哥",
        "score": 197585,
        "tag": ""
      },
      {
        "rank": 24,
        "topic": "百果园小心被消费者教育",
        "score": 186901,
        "tag": ""
      },
      {
        "rank": 25,
        "topic": "当一个人朋友圈不再更新",
        "score": 186450,
        "tag": ""
      },
      {
        "rank": 26,
        "topic": "张颜齐去毛不易家喝多睡狗窝",
        "score": 185830,
        "tag": ""
      },
      {
        "rank": 27,
        "topic": "撒贝宁保送北大的真实原因",
        "score": 183700,
        "tag": "综艺"
      },
      {
        "rank": 28,
        "topic": "蒋欣像冷宫疯掉的妃子",
        "score": 181199,
        "tag": ""
      },
      {
        "rank": 29,
        "topic": "中国海警依法对菲船予以驱离",
        "score": 179676,
        "tag": ""
      },
      {
        "rank": 30,
        "topic": "主理人不能不理人",
        "score": 177525,
        "tag": ""
      },
      {
        "rank": 31,
        "topic": "宜家宣布入驻京东",
        "score": 175471,
        "tag": ""
      },
      {
        "rank": 32,
        "topic": "苏韦达医院大屠杀",
        "score": 173227,
        "tag": ""
      },
      {
        "rank": 33,
        "topic": "社保",
        "score": 172649,
        "tag": ""
      },
      {
        "rank": 34,
        "topic": "4岁男孩从22楼窗台坠落",
        "score": 165259,
        "tag": ""
      },
      {
        "rank": 35,
        "topic": "原来焦虑抑郁的人承受力这么强",
        "score": 163484,
        "tag": ""
      },
      {
        "rank": 36,
        "topic": "日本遗孤拒做日本人并改名思华",
        "score": 158348,
        "tag": ""
      },
      {
        "rank": 37,
        "topic": "上海医保",
        "score": 149111,
        "tag": ""
      },
      {
        "rank": 38,
        "topic": "王楚钦4比0莫雷加德",
        "score": 144156,
        "tag": ""
      },
      {
        "rank": 39,
        "topic": "十万彩礼做女友造谣者凑不齐执行款",
        "score": 135860,
        "tag": ""
      },
      {
        "rank": 40,
        "topic": "婚内强奸案女方索赔30万元",
        "score": 128321,
        "tag": ""
      },
      {
        "rank": 41,
        "topic": "台湾老人夸大陆好遭女儿殴打",
        "score": 127701,
        "tag": ""
      },
      {
        "rank": 42,
        "topic": "刘宇宁第一次融入不了音乐",
        "score": 124713,
        "tag": "综艺"
      },
      {
        "rank": 43,
        "topic": "微信支付 隐私保护",
        "score": 121705,
        "tag": ""
      },
      {
        "rank": 44,
        "topic": "王楚钦说等一下让我说完",
        "score": 116765,
        "tag": ""
      },
      {
        "rank": 45,
        "topic": "张极vocal考核音色好抓耳",
        "score": 114913,
        "tag": ""
      },
      {
        "rank": 46,
        "topic": "年入百万老板去假装上班公司面试",
        "score": 113838,
        "tag": ""
      },
      {
        "rank": 47,
        "topic": "王一博正式确诊为赛博红牛",
        "score": 112767,
        "tag": ""
      },
      {
        "rank": 48,
        "topic": "这就是钢厂",
        "score": 111784,
        "tag": ""
      },
      {
        "rank": 49,
        "topic": "王玉雯是内娱幼教吧",
        "score": 111321,
        "tag": ""
      },
      {
        "rank": 50,
        "topic": "4楼开麻将馆3楼住户买震楼器反击",
        "score": 109628,
        "tag": ""
      }
    ]
  },
  {
    "time": "2025/08/11 16:36:10",
    "hots": [
      {
        "rank": 0,
        "topic": "总书记与人民在一起",
        "score": 0,
        "tag": "top"
      },
      {
        "rank": 1,
        "topic": "黄金",
        "score": 1122526,
        "tag": ""
      },
      {
        "rank": 2,
        "topic": "王玉雯 不是故意炒cp的",
        "score": 606104,
        "tag": ""
      },
      {
        "rank": 3,
        "topic": "抗战胜利80周年天安门演练现场",
        "score": 593594,
        "tag": ""
      },
      {
        "rank": 4,
        "topic": "王栎鑫苏醒吵架",
        "score": 572915,
        "tag": ""
      },
      {
        "rank": 5,
        "topic": "社保",
        "score": 563252,
        "tag": ""
      },
      {
        "rank": 6,
        "topic": "非婚生子女 育儿补贴",
        "score": 552823,
        "tag": ""
      },
      {
        "rank": 7,
        "topic": "朴彩英也给Jennie打码了",
        "score": 537022,
        "tag": ""
      },
      {
        "rank": 8,
        "topic": "龚俊王玉雯撞睡衣了",
        "score": 535407,
        "tag": "综艺"
      },
      {
        "rank": 9,
        "topic": "秦岭失联约半个月的驴友找到了",
        "score": 291272,
        "tag": ""
      },
      {
        "rank": 10,
        "topic": "未牵绳大狗扑向1岁宝宝",
        "score": 290692,
        "tag": ""
      },
      {
        "rank": 11,
        "topic": "第一次见粉丝塌房",
        "score": 287528,
        "tag": ""
      },
      {
        "rank": 12,
        "topic": "鹿晗关晓彤同款挂件",
        "score": 286649,
        "tag": ""
      },
      {
        "rank": 13,
        "topic": "花少神一季鬼一季",
        "score": 284258,
        "tag": "综艺"
      },
      {
        "rank": 14,
        "topic": "广西一女生考入清华被奖励100万元",
        "score": 281288,
        "tag": ""
      },
      {
        "rank": 15,
        "topic": "黄子韬徐艺洋婚礼能看到EXO合体吗",
        "score": 279483,
        "tag": ""
      },
      {
        "rank": 16,
        "topic": "中国好声音选手朴翔去世",
        "score": 276607,
        "tag": ""
      },
      {
        "rank": 17,
        "topic": "汪苏泷张碧晨参加东方风云榜",
        "score": 275714,
        "tag": "音乐"
      },
      {
        "rank": 18,
        "topic": "女子为避雨进彩票店顺手刮中100万",
        "score": 267209,
        "tag": ""
      },
      {
        "rank": 19,
        "topic": "全民社保要来了吗",
        "score": 261343,
        "tag": ""
      },
      {
        "rank": 20,
        "topic": "王楚钦张本智和今晚争冠",
        "score": 260221,
        "tag": ""
      },
      {
        "rank": 21,
        "topic": "怪不得医生会反复套话",
        "score": 259938,
        "tag": ""
      },
      {
        "rank": 22,
        "topic": "陶白白前妻和现任分手",
        "score": 246883,
        "tag": ""
      },
      {
        "rank": 23,
        "topic": "从毫无征兆到确诊尿毒症",
        "score": 233708,
        "tag": ""
      },
      {
        "rank": 24,
        "topic": "苏醒回应和王栎鑫吵架",
        "score": 231065,
        "tag": ""
      },
      {
        "rank": 25,
        "topic": "陈思诚带儿子为佟丽娅庆生",
        "score": 208999,
        "tag": ""
      },
      {
        "rank": 26,
        "topic": "女子为逃刑罚4年掐点怀孕连生3子",
        "score": 207688,
        "tag": ""
      },
      {
        "rank": 27,
        "topic": "浪浪山小妖怪票房超5亿",
        "score": 206314,
        "tag": "电影"
      },
      {
        "rank": 28,
        "topic": "英伟达同意向美国政府上贡15%收入",
        "score": 205554,
        "tag": ""
      },
      {
        "rank": 29,
        "topic": "献鱼把原著抠下来拍了",
        "score": 192012,
        "tag": "剧集"
      },
      {
        "rank": 30,
        "topic": "超5万元现金存取或无需登记",
        "score": 188541,
        "tag": ""
      },
      {
        "rank": 31,
        "topic": "苏韦达医院大屠杀",
        "score": 186767,
        "tag": ""
      },
      {
        "rank": 32,
        "topic": "讨厌上班的请反复看",
        "score": 180593,
        "tag": ""
      },
      {
        "rank": 33,
        "topic": "谢娜一家是现实版小巷人家吧",
        "score": 169558,
        "tag": "剧集"
      },
      {
        "rank": 34,
        "topic": "37岁发现自己断崖式衰老了",
        "score": 168413,
        "tag": ""
      },
      {
        "rank": 35,
        "topic": "十万彩礼做女友造谣者凑不齐执行款",
        "score": 154878,
        "tag": ""
      },
      {
        "rank": 36,
        "topic": "孙颖莎vs陈幸同",
        "score": 149590,
        "tag": ""
      },
      {
        "rank": 37,
        "topic": "外卖员取餐摸脸前台姑娘",
        "score": 148982,
        "tag": ""
      },
      {
        "rank": 38,
        "topic": "澳大利亚宣布将承认巴勒斯坦国",
        "score": 135816,
        "tag": ""
      },
      {
        "rank": 39,
        "topic": "利剑玫瑰豆瓣评论存在异常",
        "score": 135195,
        "tag": "剧集"
      },
      {
        "rank": 40,
        "topic": "偶遇王嘉尔骑车遛弯",
        "score": 134830,
        "tag": ""
      },
      {
        "rank": 41,
        "topic": "王楚然往台上一站就是角儿",
        "score": 134819,
        "tag": ""
      },
      {
        "rank": 42,
        "topic": "百果园小心被消费者教育",
        "score": 133086,
        "tag": ""
      },
      {
        "rank": 43,
        "topic": "问界M8纯电版静态评测",
        "score": 132724,
        "tag": ""
      },
      {
        "rank": 44,
        "topic": "婚内强奸案女方索赔30万元",
        "score": 132568,
        "tag": ""
      },
      {
        "rank": 45,
        "topic": "原来焦虑抑郁的人承受力这么强",
        "score": 122455,
        "tag": ""
      },
      {
        "rank": 46,
        "topic": "章凝成为VOGUE US主编",
        "score": 117760,
        "tag": ""
      },
      {
        "rank": 47,
        "topic": "生理性厌恶的7个躯体信号",
        "score": 115096,
        "tag": ""
      },
      {
        "rank": 48,
        "topic": "SSR级别的简历",
        "score": 110554,
        "tag": ""
      },
      {
        "rank": 49,
        "topic": "没有欧阳娣娣接不住的话",
        "score": 104148,
        "tag": "综艺"
      },
      {
        "rank": 50,
        "topic": "王楚钦将与张本智和争夺冠军",
        "score": 103592,
        "tag": ""
      }
    ]
  },
  {
    "time": "2025/08/11 17:31:13",
    "hots": [
      {
        "rank": 0,
        "topic": "总书记与人民在一起",
        "score": 0,
        "tag": "top"
      },
      {
        "rank": 1,
        "topic": "秦岭失联约半个月的驴友找到了",
        "score": 1225879,
        "tag": ""
      },
      {
        "rank": 2,
        "topic": "汪苏泷张碧晨参加东方风云榜",
        "score": 1172861,
        "tag": "综艺"
      },
      {
        "rank": 3,
        "topic": "成都世运会点火女孩滑水摘金",
        "score": 1043432,
        "tag": ""
      },
      {
        "rank": 4,
        "topic": "孙颖莎vs陈幸同",
        "score": 1013496,
        "tag": ""
      },
      {
        "rank": 5,
        "topic": "王栎鑫苏醒吵架",
        "score": 965629,
        "tag": ""
      },
      {
        "rank": 6,
        "topic": "黄金",
        "score": 947383,
        "tag": ""
      },
      {
        "rank": 7,
        "topic": "菲律宾",
        "score": 747219,
        "tag": ""
      },
      {
        "rank": 8,
        "topic": "花少神一季鬼一季",
        "score": 735465,
        "tag": "综艺"
      },
      {
        "rank": 9,
        "topic": "社保",
        "score": 644945,
        "tag": ""
      },
      {
        "rank": 10,
        "topic": "从毫无征兆到确诊尿毒症",
        "score": 624783,
        "tag": ""
      },
      {
        "rank": 11,
        "topic": "第一次见粉丝塌房",
        "score": 611958,
        "tag": ""
      },
      {
        "rank": 12,
        "topic": "鹿晗关晓彤同款挂件",
        "score": 578713,
        "tag": ""
      },
      {
        "rank": 13,
        "topic": "37岁发现自己断崖式衰老了",
        "score": 522693,
        "tag": ""
      },
      {
        "rank": 14,
        "topic": "王玉雯 不是故意炒cp的",
        "score": 436506,
        "tag": ""
      },
      {
        "rank": 15,
        "topic": "被造谣十万彩礼做女友当事人发声",
        "score": 419511,
        "tag": ""
      },
      {
        "rank": 16,
        "topic": "朴彩英也给Jennie打码了",
        "score": 416326,
        "tag": ""
      },
      {
        "rank": 17,
        "topic": "巴勒斯坦的球王贝利被以军炸死",
        "score": 390840,
        "tag": ""
      },
      {
        "rank": 18,
        "topic": "生育损伤",
        "score": 360510,
        "tag": ""
      },
      {
        "rank": 19,
        "topic": "黄子韬徐艺洋婚礼能看到EXO合体吗",
        "score": 343938,
        "tag": ""
      },
      {
        "rank": 20,
        "topic": "余景天的喝水新选择",
        "score": 293829,
        "tag": ""
      },
      {
        "rank": 21,
        "topic": "中国海警依法对菲船予以驱离",
        "score": 292441,
        "tag": ""
      },
      {
        "rank": 22,
        "topic": "苏醒让王铮亮张远打一架",
        "score": 245106,
        "tag": ""
      },
      {
        "rank": 23,
        "topic": "陶白白前妻和现任分手",
        "score": 211850,
        "tag": ""
      },
      {
        "rank": 24,
        "topic": "英伟达同意向美国政府上贡15%收入",
        "score": 186301,
        "tag": ""
      },
      {
        "rank": 25,
        "topic": "非婚生子女 育儿补贴",
        "score": 183415,
        "tag": ""
      },
      {
        "rank": 26,
        "topic": "中国好声音选手朴翔去世",
        "score": 166406,
        "tag": ""
      },
      {
        "rank": 27,
        "topic": "龚俊王玉雯撞睡衣了",
        "score": 164731,
        "tag": "综艺"
      },
      {
        "rank": 28,
        "topic": "张艺兴老板范儿",
        "score": 161465,
        "tag": ""
      },
      {
        "rank": 29,
        "topic": "许凯田曦薇子夜归人咪情未了",
        "score": 160677,
        "tag": "剧集"
      },
      {
        "rank": 30,
        "topic": "百果园的爹味教育谁买账",
        "score": 156070,
        "tag": ""
      },
      {
        "rank": 31,
        "topic": "苏韦达医院大屠杀",
        "score": 155992,
        "tag": ""
      },
      {
        "rank": 32,
        "topic": "张本智和说还差最后一步",
        "score": 155507,
        "tag": ""
      },
      {
        "rank": 33,
        "topic": "没有欧阳娣娣接不住的话",
        "score": 151427,
        "tag": "综艺"
      },
      {
        "rank": 34,
        "topic": "外卖员取餐摸脸前台姑娘",
        "score": 151384,
        "tag": ""
      },
      {
        "rank": 35,
        "topic": "艾米差点就要报警了",
        "score": 147885,
        "tag": ""
      },
      {
        "rank": 36,
        "topic": "孙颖莎正手",
        "score": 142410,
        "tag": ""
      },
      {
        "rank": 37,
        "topic": "女子为避雨进彩票店顺手刮中100万",
        "score": 137914,
        "tag": ""
      },
      {
        "rank": 38,
        "topic": "公厕下班前5分钟市民如厕被拒",
        "score": 133472,
        "tag": ""
      },
      {
        "rank": 39,
        "topic": "河南一中学官方账号回复引争议",
        "score": 132160,
        "tag": ""
      },
      {
        "rank": 40,
        "topic": "浪浪山小妖怪票房超5亿",
        "score": 130890,
        "tag": "电影"
      },
      {
        "rank": 41,
        "topic": "苏新皓的美貌朱志鑫的荣耀",
        "score": 129441,
        "tag": "综艺"
      },
      {
        "rank": 42,
        "topic": "陈思诚带儿子为佟丽娅庆生",
        "score": 128264,
        "tag": ""
      },
      {
        "rank": 43,
        "topic": "怪不得医生会反复套话",
        "score": 118061,
        "tag": ""
      },
      {
        "rank": 44,
        "topic": "孙颖莎陈幸同女单决赛赛前热身",
        "score": 117024,
        "tag": ""
      },
      {
        "rank": 45,
        "topic": "时代少年团上海站有中控",
        "score": 116858,
        "tag": "演出"
      },
      {
        "rank": 46,
        "topic": "苏新皓高精力比格犬型人格",
        "score": 115775,
        "tag": "综艺"
      },
      {
        "rank": 47,
        "topic": "女子为逃刑罚4年掐点怀孕连生3子",
        "score": 113501,
        "tag": ""
      },
      {
        "rank": 48,
        "topic": "献鱼把原著抠下来拍了",
        "score": 113221,
        "tag": "剧集"
      },
      {
        "rank": 49,
        "topic": "你可以永远相信白敬亭的审美",
        "score": 109070,
        "tag": ""
      },
      {
        "rank": 50,
        "topic": "警方回应驴友秦岭失联半个月后获救",
        "score": 107981,
        "tag": ""
      }
    ]
  },
  {
    "time": "2025/08/11 18:28:35",
    "hots": [
      {
        "rank": 0,
        "topic": "总书记与人民在一起",
        "score": 0,
        "tag": "top"
      },
      {
        "rank": 1,
        "topic": "王楚钦vs张本智和",
        "score": 1778454,
        "tag": ""
      },
      {
        "rank": 2,
        "topic": "陈幸同冠军",
        "score": 1420935,
        "tag": ""
      },
      {
        "rank": 3,
        "topic": "成都世运会点火女孩滑水摘金",
        "score": 1199776,
        "tag": ""
      },
      {
        "rank": 4,
        "topic": "孙颖莎亚军",
        "score": 1012134,
        "tag": ""
      },
      {
        "rank": 5,
        "topic": "从毫无征兆到确诊尿毒症",
        "score": 737820,
        "tag": ""
      },
      {
        "rank": 6,
        "topic": "泡泡玛特 周深",
        "score": 723546,
        "tag": ""
      },
      {
        "rank": 7,
        "topic": "菲律宾",
        "score": 693486,
        "tag": ""
      },
      {
        "rank": 8,
        "topic": "孙颖莎状态",
        "score": 690377,
        "tag": ""
      },
      {
        "rank": 9,
        "topic": "汪苏泷张碧晨参加东方风云榜",
        "score": 601053,
        "tag": "综艺"
      },
      {
        "rank": 10,
        "topic": "女孩遭轿车撞倒碾压后起身站立",
        "score": 540316,
        "tag": ""
      },
      {
        "rank": 11,
        "topic": "生育损伤",
        "score": 539719,
        "tag": ""
      },
      {
        "rank": 12,
        "topic": "王栎鑫苏醒吵架",
        "score": 539234,
        "tag": ""
      },
      {
        "rank": 13,
        "topic": "第一次见粉丝塌房",
        "score": 538445,
        "tag": ""
      },
      {
        "rank": 14,
        "topic": "鹿晗关晓彤同款挂件",
        "score": 480948,
        "tag": ""
      },
      {
        "rank": 15,
        "topic": "秦岭失联约半个月的驴友找到了",
        "score": 427026,
        "tag": ""
      },
      {
        "rank": 16,
        "topic": "花少神一季鬼一季",
        "score": 403455,
        "tag": "综艺"
      },
      {
        "rank": 17,
        "topic": "中国海警依法对菲船予以驱离",
        "score": 383761,
        "tag": ""
      },
      {
        "rank": 18,
        "topic": "朴彩英也给Jennie打码了",
        "score": 318566,
        "tag": ""
      },
      {
        "rank": 19,
        "topic": "披哥导演让许魏洲别既要又要还要",
        "score": 311652,
        "tag": ""
      },
      {
        "rank": 20,
        "topic": "王玉雯 不是故意炒cp的",
        "score": 311136,
        "tag": ""
      },
      {
        "rank": 21,
        "topic": "黄金",
        "score": 311093,
        "tag": ""
      },
      {
        "rank": 22,
        "topic": "37岁发现自己断崖式衰老了",
        "score": 310832,
        "tag": ""
      },
      {
        "rank": 23,
        "topic": "孙颖莎vs陈幸同",
        "score": 284232,
        "tag": ""
      },
      {
        "rank": 24,
        "topic": "巴勒斯坦的球王贝利被以军炸死",
        "score": 230367,
        "tag": ""
      },
      {
        "rank": 25,
        "topic": "社保",
        "score": 205634,
        "tag": ""
      },
      {
        "rank": 26,
        "topic": "很哇噻的肖战",
        "score": 204094,
        "tag": ""
      },
      {
        "rank": 27,
        "topic": "黄岩岛",
        "score": 194237,
        "tag": ""
      },
      {
        "rank": 28,
        "topic": "陈幸同会请大家吃饭",
        "score": 191073,
        "tag": ""
      },
      {
        "rank": 29,
        "topic": "赵今麦一天五套造型",
        "score": 186063,
        "tag": ""
      },
      {
        "rank": 30,
        "topic": "苏醒让王铮亮张远打一架",
        "score": 182571,
        "tag": ""
      },
      {
        "rank": 31,
        "topic": "樊振东晒第一只棒球手套",
        "score": 182088,
        "tag": ""
      },
      {
        "rank": 32,
        "topic": "奇遇值",
        "score": 147240,
        "tag": ""
      },
      {
        "rank": 33,
        "topic": "陈幸同说没想到能够胜利",
        "score": 141019,
        "tag": ""
      },
      {
        "rank": 34,
        "topic": "日本东京举行反靖国神社游行",
        "score": 136922,
        "tag": ""
      },
      {
        "rank": 35,
        "topic": "陶白白前妻和现任分手",
        "score": 125316,
        "tag": ""
      },
      {
        "rank": 36,
        "topic": "黄子韬徐艺洋婚礼能看到EXO合体吗",
        "score": 124251,
        "tag": ""
      },
      {
        "rank": 37,
        "topic": "龚俊王玉雯撞睡衣了",
        "score": 122525,
        "tag": "综艺"
      },
      {
        "rank": 38,
        "topic": "中国好声音选手朴翔去世",
        "score": 116419,
        "tag": ""
      },
      {
        "rank": 39,
        "topic": "拿两份工资的退休人",
        "score": 113060,
        "tag": ""
      },
      {
        "rank": 40,
        "topic": "5名记者被以军炸死",
        "score": 112011,
        "tag": ""
      },
      {
        "rank": 41,
        "topic": "DeepSeek母公司总监套取券商上亿佣金",
        "score": 111474,
        "tag": ""
      },
      {
        "rank": 42,
        "topic": "田曦薇好会跑",
        "score": 103411,
        "tag": "剧集"
      },
      {
        "rank": 43,
        "topic": "河南一中学官方账号回复引争议",
        "score": 103121,
        "tag": ""
      },
      {
        "rank": 44,
        "topic": "陈飞宇顶级魅魔",
        "score": 99654,
        "tag": ""
      },
      {
        "rank": 45,
        "topic": "陈思诚带儿子为佟丽娅庆生",
        "score": 99560,
        "tag": ""
      },
      {
        "rank": 46,
        "topic": "英伟达同意向美国政府上贡15%收入",
        "score": 98688,
        "tag": ""
      },
      {
        "rank": 47,
        "topic": "苏韦达医院大屠杀",
        "score": 96749,
        "tag": ""
      },
      {
        "rank": 48,
        "topic": "苏新皓的美貌朱志鑫的荣耀",
        "score": 96568,
        "tag": "综艺"
      },
      {
        "rank": 49,
        "topic": "5小时法则",
        "score": 96518,
        "tag": ""
      },
      {
        "rank": 50,
        "topic": "建议少用爆冷这个词",
        "score": 95261,
        "tag": ""
      }
    ]
  }
]